Workbook

Sheet Shopping
A2: TOPIC: FROM MORNING TO NIGHT
A3: No | B3: No | C3: ID | D3: Sentence | E3: Type | F3: Link | G3: ID | H3: Copy Google drive to …
B4: 1 | C4: =B4&E4 -> 1Struc | D4: S + GOT + NOUN + WHOLESALE… /… mua giá sỉ/ | E4: Struc
B5: 1.1 | C5: =B5&E5 -> 1.1Viet | D5: Tôi đã mua tất giá sỉ. | E5: Viet | F5: =IF(G5="","","https://docs.google.com/uc?export=download&id="&G5) | G5: =IFERROR(LEFT(RIGHT(H5,LEN(H5)-32),LEN(RIGHT(H5,LEN(H5)-32))-17),"")
A6: 1 | B6: 1.1 | C6: =B6&E6 -> 1.1Eng | D6: I got my socks wholesale. | E6: Eng | F6: =IF(G6="","","https://docs.google.com/uc?export=download&id="&G6) -> https://docs.google.com/uc?export=download&id=1QvqycNx3JcG4G4TVHgXp1tDY_xL-WlxL | G6: =IFERROR(LEFT(RIGHT(H6,LEN(H6)-32),LEN(RIGHT(H6,LEN(H6)-32))-17),"") -> 1QvqycNx3JcG4G4TVHgXp1tDY_xL-WlxL | H6: https://drive.google.com/file/d/1QvqycNx3JcG4G4TVHgXp1tDY_xL-WlxL/view?usp=sharing
B7: 1.1 | C7: =B7&E7 -> 1.1Phon | D7: aɪ ga:t maɪ sa:ks ˈhoʊlseɪl | E7: Phon | F7: =IF(G7="","","https://docs.google.com/uc?export=download&id="&G7) | G7: =IFERROR(LEFT(RIGHT(H7,LEN(H7)-32),LEN(RIGHT(H7,LEN(H7)-32))-17),"")
B8: 1.2 | C8: =B8&E8 -> 1.2Viet | D8: Tôi đã mua quần áo giá sỉ. | E8: Viet | F8: =IF(G8="","","https://docs.google.com/uc?export=download&id="&G8) | G8: =IFERROR(LEFT(RIGHT(H8,LEN(H8)-32),LEN(RIGHT(H8,LEN(H8)-32))-17),"")
A9: =+A6+1 -> 2 | B9: =B8 -> 1.2 | C9: =B9&E9 -> 1.2Eng | D9: I got my clothes wholesale. | E9: Eng | F9: =IF(G9="","","https://docs.google.com/uc?export=download&id="&G9) -> https://docs.google.com/uc?export=download&id=1vasjBVqETqOl7bs3vQBOAzR4NiGpoxsF | G9: =IFERROR(LEFT(RIGHT(H9,LEN(H9)-32),LEN(RIGHT(H9,LEN(H9)-32))-17),"") -> 1vasjBVqETqOl7bs3vQBOAzR4NiGpoxsF | H9: https://drive.google.com/file/d/1vasjBVqETqOl7bs3vQBOAzR4NiGpoxsF/view?usp=sharing
B10: =B9 -> 1.2 | C10: =B10&E10 -> 1.2Phon | D10: aɪ ga:t maɪ kloʊðz ˈhoʊlseɪl | E10: Phon | F10: =IF(G10="","","https://docs.google.com/uc?export=download&id="&G10) | G10: =IFERROR(LEFT(RIGHT(H10,LEN(H10)-32),LEN(RIGHT(H10,LEN(H10)-32))-17),"")
B11: 1.3 | C11: =B11&E11 -> 1.3Viet | D11: Chị ấy mua bóng đèn trang trí với giá sỉ. | E11: Viet | F11: =IF(G11="","","https://docs.google.com/uc?export=download&id="&G11) | G11: =IFERROR(LEFT(RIGHT(H11,LEN(H11)-32),LEN(RIGHT(H11,LEN(H11)-32))-17),"")
A12: =+A9+1 -> 3 | B12: =B11 -> 1.3 | C12: =B12&E12 -> 1.3Eng | D12: She got decorative lights wholesale. | E12: Eng | F12: =IF(G12="","","https://docs.google.com/uc?export=download&id="&G12) -> https://docs.google.com/uc?export=download&id=1peXZA3soILfxKtdaD4T537d9LgVveBzE | G12: =IFERROR(LEFT(RIGHT(H12,LEN(H12)-32),LEN(RIGHT(H12,LEN(H12)-32))-17),"") -> 1peXZA3soILfxKtdaD4T537d9LgVveBzE | H12: https://drive.google.com/file/d/1peXZA3soILfxKtdaD4T537d9LgVveBzE/view?usp=sharing
B13: =B12 -> 1.3 | C13: =B13&E13 -> 1.3Phon | D13: ʃi: ga:t ˈdɛkrətɪv laɪts ˈhoʊlseɪl | E13: Phon | F13: =IF(G13="","","https://docs.google.com/uc?export=download&id="&G13) | G13: =IFERROR(LEFT(RIGHT(H13,LEN(H13)-32),LEN(RIGHT(H13,LEN(H13)-32))-17),"")
B14: 1.4 | C14: =B14&E14 -> 1.4Viet | D14: Anh ấy mua rượu với giá sỉ. | E14: Viet | F14: =IF(G14="","","https://docs.google.com/uc?export=download&id="&G14) | G14: =IFERROR(LEFT(RIGHT(H14,LEN(H14)-32),LEN(RIGHT(H14,LEN(H14)-32))-17),"")
A15: =+A12+1 -> 4 | B15: =B14 -> 1.4 | C15: =B15&E15 -> 1.4Eng | D15: He got wine wholesale. | E15: Eng | F15: =IF(G15="","","https://docs.google.com/uc?export=download&id="&G15) -> https://docs.google.com/uc?export=download&id=1lpbZ84Z9-7MbW-sErkcSGi88_7MjVpSa | G15: =IFERROR(LEFT(RIGHT(H15,LEN(H15)-32),LEN(RIGHT(H15,LEN(H15)-32))-17),"") -> 1lpbZ84Z9-7MbW-sErkcSGi88_7MjVpSa | H15: https://drive.google.com/file/d/1lpbZ84Z9-7MbW-sErkcSGi88_7MjVpSa/view?usp=sharing
B16: =B15 -> 1.4 | C16: =B16&E16 -> 1.4Phon | D16: hi: ga:t waɪn ˈhoʊlseɪl | E16: Phon | F16: =IF(G16="","","https://docs.google.com/uc?export=download&id="&G16) | G16: =IFERROR(LEFT(RIGHT(H16,LEN(H16)-32),LEN(RIGHT(H16,LEN(H16)-32))-17),"")
B17: 2 | C17: =B17&E17 -> 2Struc | D17: S + TO BE SOLD AT HALF PRICE… /Cái gì đó bán nửa giá…/ | E17: Struc | F17: =IF(G17="","","https://docs.google.com/uc?export=download&id="&G17) | G17: =IFERROR(LEFT(RIGHT(H17,LEN(H17)-32),LEN(RIGHT(H17,LEN(H17)-32))-17),"")
B18: 2.1 | C18: =B18&E18 -> 2.1Viet | D18: Hàng sản xuất dư được bán nửa giá. | E18: Viet | F18: =IF(G18="","","https://docs.google.com/uc?export=download&id="&G18) | G18: =IFERROR(LEFT(RIGHT(H18,LEN(H18)-32),LEN(RIGHT(H18,LEN(H18)-32))-17),"")
A19: =A15+1 -> 5 | B19: =B18 -> 2.1 | C19: =B19&E19 -> 2.1Eng | D19: Surplus goods are sold at half price. | E19: Eng | F19: =IF(G19="","","https://docs.google.com/uc?export=download&id="&G19) -> https://docs.google.com/uc?export=download&id=1dGzVe3ZtjEoDcPRMJotwSrA9aF9xdm3Z | G19: =IFERROR(LEFT(RIGHT(H19,LEN(H19)-32),LEN(RIGHT(H19,LEN(H19)-32))-17),"") -> 1dGzVe3ZtjEoDcPRMJotwSrA9aF9xdm3Z | H19: https://drive.google.com/file/d/1dGzVe3ZtjEoDcPRMJotwSrA9aF9xdm3Z/view?usp=sharing
B20: =B19 -> 2.1 | C20: =B20&E20 -> 2.1Phon | D20: ˈsɜ:rpləs gʊdz a:r soʊld æt hæf praɪs | E20: Phon | F20: =IF(G20="","","https://docs.google.com/uc?export=download&id="&G20) | G20: =IFERROR(LEFT(RIGHT(H20,LEN(H20)-32),LEN(RIGHT(H20,LEN(H20)-32))-17),"")
B21: 2.2 | C21: =B21&E21 -> 2.2Viet | D21: Cuốn sách này được bán với nửa giá. | E21: Viet | F21: =IF(G21="","","https://docs.google.com/uc?export=download&id="&G21) | G21: =IFERROR(LEFT(RIGHT(H21,LEN(H21)-32),LEN(RIGHT(H21,LEN(H21)-32))-17),"")
A22: =+A19+1 -> 6 | B22: =B21 -> 2.2 | C22: =B22&E22 -> 2.2Eng | D22: This book is sold at half price. | E22: Eng | F22: =IF(G22="","","https://docs.google.com/uc?export=download&id="&G22) -> https://docs.google.com/uc?export=download&id=1bE7kOP2RQNucQ7RbAkn0PeoO6yw_Dd_5 | G22: =IFERROR(LEFT(RIGHT(H22,LEN(H22)-32),LEN(RIGHT(H22,LEN(H22)-32))-17),"") -> 1bE7kOP2RQNucQ7RbAkn0PeoO6yw_Dd_5 | H22: https://drive.google.com/file/d/1bE7kOP2RQNucQ7RbAkn0PeoO6yw_Dd_5/view?usp=sharing
B23: =B22 -> 2.2 | C23: =B23&E23 -> 2.2Phon | D23: ðɪs bʊk ɪz soʊld æt hæf praɪs | E23: Phon | F23: =IF(G23="","","https://docs.google.com/uc?export=download&id="&G23) | G23: =IFERROR(LEFT(RIGHT(H23,LEN(H23)-32),LEN(RIGHT(H23,LEN(H23)-32))-17),"")
B24: 2.3 | C24: =B24&E24 -> 2.3Viet | D24: Mấy cái bánh pizza này được bán với nửa giá. | E24: Viet | F24: =IF(G24="","","https://docs.google.com/uc?export=download&id="&G24) | G24: =IFERROR(LEFT(RIGHT(H24,LEN(H24)-32),LEN(RIGHT(H24,LEN(H24)-32))-17),"")
A25: =+A22+1 -> 7 | B25: =B24 -> 2.3 | C25: =B25&E25 -> 2.3Eng | D25: These pizzas are sold at half price. | E25: Eng | F25: =IF(G25="","","https://docs.google.com/uc?export=download&id="&G25) -> https://docs.google.com/uc?export=download&id=1dj-mw8sQJcgFasY1pHP2zdirU8iZ-gOn | G25: =IFERROR(LEFT(RIGHT(H25,LEN(H25)-32),LEN(RIGHT(H25,LEN(H25)-32))-17),"") -> 1dj-mw8sQJcgFasY1pHP2zdirU8iZ-gOn | H25: https://drive.google.com/file/d/1dj-mw8sQJcgFasY1pHP2zdirU8iZ-gOn/view?usp=sharing
B26: =B25 -> 2.3 | C26: =B26&E26 -> 2.3Phon | D26: ði:z ˈpi:tsəz a:r soʊld æt hæf praɪs | E26: Phon | F26: =IF(G26="","","https://docs.google.com/uc?export=download&id="&G26) | G26: =IFERROR(LEFT(RIGHT(H26,LEN(H26)-32),LEN(RIGHT(H26,LEN(H26)-32))-17),"")
B27: 2.4 | C27: =B27&E27 -> 2.4Viet | D27: Mặt hàng này được bán nửa giá. | E27: Viet | F27: =IF(G27="","","https://docs.google.com/uc?export=download&id="&G27) | G27: =IFERROR(LEFT(RIGHT(H27,LEN(H27)-32),LEN(RIGHT(H27,LEN(H27)-32))-17),"")
A28: =+A25+1 -> 8 | B28: =B27 -> 2.4 | C28: =B28&E28 -> 2.4Eng | D28: This product/item is sold at half price. | E28: Eng | F28: =IF(G28="","","https://docs.google.com/uc?export=download&id="&G28) -> https://docs.google.com/uc?export=download&id=1Hp-h5XxwC5tGc8dxmnXl11DIn6a14Zcr | G28: =IFERROR(LEFT(RIGHT(H28,LEN(H28)-32),LEN(RIGHT(H28,LEN(H28)-32))-17),"") -> 1Hp-h5XxwC5tGc8dxmnXl11DIn6a14Zcr | H28: https://drive.google.com/file/d/1Hp-h5XxwC5tGc8dxmnXl11DIn6a14Zcr/view?usp=sharing
B29: =B28 -> 2.4 | C29: =B29&E29 -> 2.4Phon | D29: ðɪs ˈpra:dʌkt/ˈaɪtəm ɪz soʊld æt hæf praɪs | E29: Phon | F29: =IF(G29="","","https://docs.google.com/uc?export=download&id="&G29) | G29: =IFERROR(LEFT(RIGHT(H29,LEN(H29)-32),LEN(RIGHT(H29,LEN(H29)-32))-17),"")
B30: 3 | C30: =B30&E30 -> 3Struc | D30: S + ONLY BUY BRAND-NAME PRODUCTS… /Ai đó chỉ mua hàng có thương hiệu…/ | E30: Struc | F30: =IF(G30="","","https://docs.google.com/uc?export=download&id="&G30) | G30: =IFERROR(LEFT(RIGHT(H30,LEN(H30)-32),LEN(RIGHT(H30,LEN(H30)-32))-17),"")
B31: 3.1 | C31: =B31&E31 -> 3.1Viet | D31: Bố mình chỉ mua hàng có thương hiệu. | E31: Viet | F31: =IF(G31="","","https://docs.google.com/uc?export=download&id="&G31) | G31: =IFERROR(LEFT(RIGHT(H31,LEN(H31)-32),LEN(RIGHT(H31,LEN(H31)-32))-17),"")
A32: 9 | B32: =B31 -> 3.1 | C32: =B32&E32 -> 3.1Eng | D32: My dad only buys brand-name products. | E32: Eng | F32: =IF(G32="","","https://docs.google.com/uc?export=download&id="&G32) -> https://docs.google.com/uc?export=download&id=1-UhOlY1W8cuYL3nsSEckPWi4jEUoztWj | G32: =IFERROR(LEFT(RIGHT(H32,LEN(H32)-32),LEN(RIGHT(H32,LEN(H32)-32))-17),"") -> 1-UhOlY1W8cuYL3nsSEckPWi4jEUoztWj | H32: https://drive.google.com/file/d/1-UhOlY1W8cuYL3nsSEckPWi4jEUoztWj/view?usp=sharing
B33: =B32 -> 3.1 | C33: =B33&E33 -> 3.1Phon | D33: maɪ dæd ˈoʊnli baɪz brænd neɪm ˈpra:dʌkts | E33: Phon | F33: =IF(G33="","","https://docs.google.com/uc?export=download&id="&G33) | G33: =IFERROR(LEFT(RIGHT(H33,LEN(H33)-32),LEN(RIGHT(H33,LEN(H33)-32))-17),"")
B34: 3.2 | C34: =B34&E34 -> 3.2Viet | D34: Tôi chỉ mua giày có thương hiệu. | E34: Viet | F34: =IF(G34="","","https://docs.google.com/uc?export=download&id="&G34) | G34: =IFERROR(LEFT(RIGHT(H34,LEN(H34)-32),LEN(RIGHT(H34,LEN(H34)-32))-17),"")
A35: 10 | B35: =B34 -> 3.2 | C35: =B35&E35 -> 3.2Eng | D35: I only buy brand-name shoes. | E35: Eng | F35: =IF(G35="","","https://docs.google.com/uc?export=download&id="&G35) -> https://docs.google.com/uc?export=download&id=1sdtdrAYSm7wZwZPvc1IqZzv4wJifJfrW | G35: =IFERROR(LEFT(RIGHT(H35,LEN(H35)-32),LEN(RIGHT(H35,LEN(H35)-32))-17),"") -> 1sdtdrAYSm7wZwZPvc1IqZzv4wJifJfrW | H35: https://drive.google.com/file/d/1sdtdrAYSm7wZwZPvc1IqZzv4wJifJfrW/view?usp=sharing
B36: =B35 -> 3.2 | C36: =B36&E36 -> 3.2Phon | D36: aɪ ˈoʊnli baɪ brænd neɪm ʃu:z | E36: Phon | F36: =IF(G36="","","https://docs.google.com/uc?export=download&id="&G36) | G36: =IFERROR(LEFT(RIGHT(H36,LEN(H36)-32),LEN(RIGHT(H36,LEN(H36)-32))-17),"")
B37: 3.3 | C37: =B37&E37 -> 3.3Viet | D37: Mẹ tôi chỉ mua mắt kính có thương hiệu. | E37: Viet | F37: =IF(G37="","","https://docs.google.com/uc?export=download&id="&G37) | G37: =IFERROR(LEFT(RIGHT(H37,LEN(H37)-32),LEN(RIGHT(H37,LEN(H37)-32))-17),"")
A38: 11 | B38: =B37 -> 3.3 | C38: =B38&E38 -> 3.3Eng | D38: My mom only buys brand-name glasses. | E38: Eng | F38: =IF(G38="","","https://docs.google.com/uc?export=download&id="&G38) -> https://docs.google.com/uc?export=download&id=10u_HCX9arQY1jlRlG1z5K2HgwDSmOXSz | G38: =IFERROR(LEFT(RIGHT(H38,LEN(H38)-32),LEN(RIGHT(H38,LEN(H38)-32))-17),"") -> 10u_HCX9arQY1jlRlG1z5K2HgwDSmOXSz | H38: https://drive.google.com/file/d/10u_HCX9arQY1jlRlG1z5K2HgwDSmOXSz/view?usp=sharing
B39: =B38 -> 3.3 | C39: =B39&E39 -> 3.3Phon | D39: maɪ ma:m ˈoʊnli baɪz brænd neɪm ˈglæsəz | E39: Phon | F39: =IF(G39="","","https://docs.google.com/uc?export=download&id="&G39) | G39: =IFERROR(LEFT(RIGHT(H39,LEN(H39)-32),LEN(RIGHT(H39,LEN(H39)-32))-17),"")
B40: 3.4 | C40: =B40&E40 -> 3.4Viet | D40: Tôi chỉ mua giỏ xách có thương hiệu. | E40: Viet | F40: =IF(G40="","","https://docs.google.com/uc?export=download&id="&G40) | G40: =IFERROR(LEFT(RIGHT(H40,LEN(H40)-32),LEN(RIGHT(H40,LEN(H40)-32))-17),"")
A41: 12 | B41: =B40 -> 3.4 | C41: =B41&E41 -> 3.4Eng | D41: I only buy brand-name handbag. | E41: Eng | F41: =IF(G41="","","https://docs.google.com/uc?export=download&id="&G41) -> https://docs.google.com/uc?export=download&id=1DxwV84b1d-9Q1CeTOntziHsKh3lEtmJ1 | G41: =IFERROR(LEFT(RIGHT(H41,LEN(H41)-32),LEN(RIGHT(H41,LEN(H41)-32))-17),"") -> 1DxwV84b1d-9Q1CeTOntziHsKh3lEtmJ1 | H41: https://drive.google.com/file/d/1DxwV84b1d-9Q1CeTOntziHsKh3lEtmJ1/view?usp=sharing
B42: =B41 -> 3.4 | C42: =B42&E42 -> 3.4Phon | D42: aɪ ˈoʊnli baɪ brænd neɪm ˈhændbæg | E42: Phon | F42: =IF(G42="","","https://docs.google.com/uc?export=download&id="&G42) | G42: =IFERROR(LEFT(RIGHT(H42,LEN(H42)-32),LEN(RIGHT(H42,LEN(H42)-32))-17),"")
B43: 4 | C43: =B43&E43 -> 4Struc | D43: PLACE + IS ALWAYS CROWDED… /Nơi nào đó lúc nào cũng đông đúc…/ | E43: Struc | F43: =IF(G43="","","https://docs.google.com/uc?export=download&id="&G43) | G43: =IFERROR(LEFT(RIGHT(H43,LEN(H43)-32),LEN(RIGHT(H43,LEN(H43)-32))-17),"")
B44: 4.1 | C44: =B44&E44 -> 4.1Viet | D44: Chợ đêm ở Đà Lạt lúc nào cũng đông. | E44: Viet | F44: =IF(G44="","","https://docs.google.com/uc?export=download&id="&G44) | G44: =IFERROR(LEFT(RIGHT(H44,LEN(H44)-32),LEN(RIGHT(H44,LEN(H44)-32))-17),"")
A45: 13 | B45: =B44 -> 4.1 | C45: =B45&E45 -> 4.1Eng | D45: The night market in Da Lat is always crowded. | E45: Eng | F45: =IF(G45="","","https://docs.google.com/uc?export=download&id="&G45) -> https://docs.google.com/uc?export=download&id=1DKxc5zHfNWgXFv5C5UZ4RiRNPPfxNORG | G45: =IFERROR(LEFT(RIGHT(H45,LEN(H45)-32),LEN(RIGHT(H45,LEN(H45)-32))-17),"") -> 1DKxc5zHfNWgXFv5C5UZ4RiRNPPfxNORG | H45: https://drive.google.com/file/d/1DKxc5zHfNWgXFv5C5UZ4RiRNPPfxNORG/view?usp=sharing
B46: =B45 -> 4.1 | C46: =B46&E46 -> 4.1Phon | D46: ðə naɪt ˈma:rkɪt ɪn Da Lat ɪz ˈa:lweɪz ˈkraʊdɪd | E46: Phon | F46: =IF(G46="","","https://docs.google.com/uc?export=download&id="&G46) | G46: =IFERROR(LEFT(RIGHT(H46,LEN(H46)-32),LEN(RIGHT(H46,LEN(H46)-32))-17),"")
B47: 4.2 | C47: =B47&E47 -> 4.2Viet | D47: Chợ nông sản lúc nào cũng đông. | E47: Viet | F47: =IF(G47="","","https://docs.google.com/uc?export=download&id="&G47) | G47: =IFERROR(LEFT(RIGHT(H47,LEN(H47)-32),LEN(RIGHT(H47,LEN(H47)-32))-17),"")
A48: 14 | B48: =B47 -> 4.2 | C48: =B48&E48 -> 4.2Eng | D48: Farmer’s market is always crowded. | E48: Eng | F48: =IF(G48="","","https://docs.google.com/uc?export=download&id="&G48) -> https://docs.google.com/uc?export=download&id=1OsALbANzgaMBu6jxjK_BHk7koe-A0xS4 | G48: =IFERROR(LEFT(RIGHT(H48,LEN(H48)-32),LEN(RIGHT(H48,LEN(H48)-32))-17),"") -> 1OsALbANzgaMBu6jxjK_BHk7koe-A0xS4 | H48: https://drive.google.com/file/d/1OsALbANzgaMBu6jxjK_BHk7koe-A0xS4/view?usp=sharing
B49: =B48 -> 4.2 | C49: =B49&E49 -> 4.2Phon | D49: ˈfa:rmərz ˈma:rkɪt ɪz ˈa:lweɪz ˈkraʊdɪd | E49: Phon | F49: =IF(G49="","","https://docs.google.com/uc?export=download&id="&G49) | G49: =IFERROR(LEFT(RIGHT(H49,LEN(H49)-32),LEN(RIGHT(H49,LEN(H49)-32))-17),"")
B50: 4.3 | C50: =B50&E50 -> 4.3Viet | D50: Chợ đồ cũ lúc nào cũng đông. | E50: Viet | F50: =IF(G50="","","https://docs.google.com/uc?export=download&id="&G50) | G50: =IFERROR(LEFT(RIGHT(H50,LEN(H50)-32),LEN(RIGHT(H50,LEN(H50)-32))-17),"")
A51: 15 | B51: =B50 -> 4.3 | C51: =B51&E51 -> 4.3Eng | D51: Flea market is always crowded. | E51: Eng | F51: =IF(G51="","","https://docs.google.com/uc?export=download&id="&G51) -> https://docs.google.com/uc?export=download&id=1RYNg-8T-SxcrEK0YswA-crQruQG2sFqE | G51: =IFERROR(LEFT(RIGHT(H51,LEN(H51)-32),LEN(RIGHT(H51,LEN(H51)-32))-17),"") -> 1RYNg-8T-SxcrEK0YswA-crQruQG2sFqE | H51: https://drive.google.com/file/d/1RYNg-8T-SxcrEK0YswA-crQruQG2sFqE/view?usp=sharing
B52: =B51 -> 4.3 | C52: =B52&E52 -> 4.3Phon | D52: fli: ˈma:rkɪt ɪz ˈa:lweɪz ˈkraʊdɪd | E52: Phon | F52: =IF(G52="","","https://docs.google.com/uc?export=download&id="&G52) | G52: =IFERROR(LEFT(RIGHT(H52,LEN(H52)-32),LEN(RIGHT(H52,LEN(H52)-32))-17),"")
B53: 4.4 | C53: =B53&E53 -> 4.4Viet | D53: Siêu thị lúc nào cũng đông. | E53: Viet | F53: =IF(G53="","","https://docs.google.com/uc?export=download&id="&G53) | G53: =IFERROR(LEFT(RIGHT(H53,LEN(H53)-32),LEN(RIGHT(H53,LEN(H53)-32))-17),"")
A54: 16 | B54: =B53 -> 4.4 | C54: =B54&E54 -> 4.4Eng | D54: The supermarket is always crowded. | E54: Eng | F54: =IF(G54="","","https://docs.google.com/uc?export=download&id="&G54) -> https://docs.google.com/uc?export=download&id=1aSN4MLuxrmf41BR98TlgYTcO8q6Hixij | G54: =IFERROR(LEFT(RIGHT(H54,LEN(H54)-32),LEN(RIGHT(H54,LEN(H54)-32))-17),"") -> 1aSN4MLuxrmf41BR98TlgYTcO8q6Hixij | H54: https://drive.google.com/file/d/1aSN4MLuxrmf41BR98TlgYTcO8q6Hixij/view?usp=sharing
B55: =B54 -> 4.4 | C55: =B55&E55 -> 4.4Phon | D55: ðə ˈsu:pərma:rkɪt ɪz ˈa:lweɪz ˈkraʊdɪd | E55: Phon | F55: =IF(G55="","","https://docs.google.com/uc?export=download&id="&G55) | G55: =IFERROR(LEFT(RIGHT(H55,LEN(H55)-32),LEN(RIGHT(H55,LEN(H55)-32))-17),"")
B56: 4.5 | C56: =B56&E56 -> 4.5Viet | D56: Chợ ngoài trời lúc nào cũng đông. | E56: Viet | F56: =IF(G56="","","https://docs.google.com/uc?export=download&id="&G56) | G56: =IFERROR(LEFT(RIGHT(H56,LEN(H56)-32),LEN(RIGHT(H56,LEN(H56)-32))-17),"")
A57: 17 | B57: =B56 -> 4.5 | C57: =B57&E57 -> 4.5Eng | D57: The street market is always crowded. | E57: Eng | F57: =IF(G57="","","https://docs.google.com/uc?export=download&id="&G57) -> https://docs.google.com/uc?export=download&id=1oJZKn28iyyW1YLr55FvAHVqg4wdYcxvH | G57: =IFERROR(LEFT(RIGHT(H57,LEN(H57)-32),LEN(RIGHT(H57,LEN(H57)-32))-17),"") -> 1oJZKn28iyyW1YLr55FvAHVqg4wdYcxvH | H57: https://drive.google.com/file/d/1oJZKn28iyyW1YLr55FvAHVqg4wdYcxvH/view?usp=sharing
B58: =B57 -> 4.5 | C58: =B58&E58 -> 4.5Phon | D58: ðə stri:t ˈma:rkɪt ɪz ˈa:lweɪz ˈkraʊdɪd | E58: Phon | F58: =IF(G58="","","https://docs.google.com/uc?export=download&id="&G58) | G58: =IFERROR(LEFT(RIGHT(H58,LEN(H58)-32),LEN(RIGHT(H58,LEN(H58)-32))-17),"")
B59: 5 | C59: =B59&E59 -> 5Struc | D59: THIS IS THE ONLY PLACE THAT SELLS + NOUN /Đây là nơi duy nhất bán…/ | E59: Struc | F59: =IF(G59="","","https://docs.google.com/uc?export=download&id="&G59) | G59: =IFERROR(LEFT(RIGHT(H59,LEN(H59)-32),LEN(RIGHT(H59,LEN(H59)-32))-17),"")
B60: 5.1 | C60: =B60&E60 -> 5.1Viet | D60: Đây là nơi duy nhất bán đồ thủ công mỹ nghệ. | E60: Viet | F60: =IF(G60="","","https://docs.google.com/uc?export=download&id="&G60) | G60: =IFERROR(LEFT(RIGHT(H60,LEN(H60)-32),LEN(RIGHT(H60,LEN(H60)-32))-17),"")
A61: 18 | B61: =B60 -> 5.1 | C61: =B61&E61 -> 5.1Eng | D61: This is the only place that sells arts and crafts. | E61: Eng | F61: =IF(G61="","","https://docs.google.com/uc?export=download&id="&G61) -> https://docs.google.com/uc?export=download&id=1-YcvqlJjdZSA0TmV4uAr3rLIGBbp1XA5 | G61: =IFERROR(LEFT(RIGHT(H61,LEN(H61)-32),LEN(RIGHT(H61,LEN(H61)-32))-17),"") -> 1-YcvqlJjdZSA0TmV4uAr3rLIGBbp1XA5 | H61: https://drive.google.com/file/d/1-YcvqlJjdZSA0TmV4uAr3rLIGBbp1XA5/view?usp=sharing
B62: =B61 -> 5.1 | C62: =B62&E62 -> 5.1Phon | D62: ðɪs ɪz ði: ˈoʊnli pleɪs ðæt sɛlz a:rts ænd cræfts | E62: Phon | F62: =IF(G62="","","https://docs.google.com/uc?export=download&id="&G62) | G62: =IFERROR(LEFT(RIGHT(H62,LEN(H62)-32),LEN(RIGHT(H62,LEN(H62)-32))-17),"")
B63: 5.2 | C63: =B63&E63 -> 5.2Viet | D63: Đây là nơi duy nhất bán đồ làm bằng tay. | E63: Viet | F63: =IF(G63="","","https://docs.google.com/uc?export=download&id="&G63) | G63: =IFERROR(LEFT(RIGHT(H63,LEN(H63)-32),LEN(RIGHT(H63,LEN(H63)-32))-17),"")
A64: 19 | B64: =B63 -> 5.2 | C64: =B64&E64 -> 5.2Eng | D64: This is the only place that sells handmade. | E64: Eng | F64: =IF(G64="","","https://docs.google.com/uc?export=download&id="&G64) -> https://docs.google.com/uc?export=download&id=1OuwEgzWbwGqeCqtcCnE2AJZoQX4Bp5vx | G64: =IFERROR(LEFT(RIGHT(H64,LEN(H64)-32),LEN(RIGHT(H64,LEN(H64)-32))-17),"") -> 1OuwEgzWbwGqeCqtcCnE2AJZoQX4Bp5vx | H64: https://drive.google.com/file/d/1OuwEgzWbwGqeCqtcCnE2AJZoQX4Bp5vx/view?usp=sharing
B65: =B64 -> 5.2 | C65: =B65&E65 -> 5.2Phon | D65: ðɪs ɪz ði: ˈoʊnli pleɪs ðæt sɛlz hændˈmeɪd | E65: Phon | F65: =IF(G65="","","https://docs.google.com/uc?export=download&id="&G65) | G65: =IFERROR(LEFT(RIGHT(H65,LEN(H65)-32),LEN(RIGHT(H65,LEN(H65)-32))-17),"")
B66: 5.3 | C66: =B66&E66 -> 5.3Viet | D66: Đây là nơi duy nhất bán trứng gà thả vườn và thực phẩm hữu cơ. | E66: Viet | F66: =IF(G66="","","https://docs.google.com/uc?export=download&id="&G66) | G66: =IFERROR(LEFT(RIGHT(H66,LEN(H66)-32),LEN(RIGHT(H66,LEN(H66)-32))-17),"")
A67: 20 | B67: =B66 -> 5.3 | C67: =B67&E67 -> 5.3Eng | D67: This is the only place that sells free-range eggs and organic food. | E67: Eng | F67: =IF(G67="","","https://docs.google.com/uc?export=download&id="&G67) -> https://docs.google.com/uc?export=download&id=1RqT1eZo2TMTOclPTA_vh_ep71xrgY6Up | G67: =IFERROR(LEFT(RIGHT(H67,LEN(H67)-32),LEN(RIGHT(H67,LEN(H67)-32))-17),"") -> 1RqT1eZo2TMTOclPTA_vh_ep71xrgY6Up | H67: https://drive.google.com/file/d/1RqT1eZo2TMTOclPTA_vh_ep71xrgY6Up/view?usp=sharing
B68: =B67 -> 5.3 | C68: =B68&E68 -> 5.3Phon | D68: ðɪs ɪz ði: ˈoʊnli pleɪs ðæt sɛlz fri: reɪnʤ ɛgz ænd ɔ:rˈgænɪk fu:d | E68: Phon | F68: =IF(G68="","","https://docs.google.com/uc?export=download&id="&G68) | G68: =IFERROR(LEFT(RIGHT(H68,LEN(H68)-32),LEN(RIGHT(H68,LEN(H68)-32))-17),"")
B69: 5.4 | C69: =B69&E69 -> 5.4Viet | D69: Đây là nơi duy nhất bán đồ đã qua sử dụng. | E69: Viet | F69: =IF(G69="","","https://docs.google.com/uc?export=download&id="&G69) | G69: =IFERROR(LEFT(RIGHT(H69,LEN(H69)-32),LEN(RIGHT(H69,LEN(H69)-32))-17),"")
A70: 21 | B70: =B69 -> 5.4 | C70: =B70&E70 -> 5.4Eng | D70: This is the only place that sells second-hand. | E70: Eng | F70: =IF(G70="","","https://docs.google.com/uc?export=download&id="&G70) -> https://docs.google.com/uc?export=download&id=1bMn7aasXXYVVwWbbKIoSuZOb6m9dK2Kd | G70: =IFERROR(LEFT(RIGHT(H70,LEN(H70)-32),LEN(RIGHT(H70,LEN(H70)-32))-17),"") -> 1bMn7aasXXYVVwWbbKIoSuZOb6m9dK2Kd | H70: https://drive.google.com/file/d/1bMn7aasXXYVVwWbbKIoSuZOb6m9dK2Kd/view?usp=sharing
B71: =B70 -> 5.4 | C71: =B71&E71 -> 5.4Phon | D71: ðɪs ɪz ði: ˈoʊnli pleɪs ðæt sɛlz ˈsɛkənd hænd | E71: Phon | F71: =IF(G71="","","https://docs.google.com/uc?export=download&id="&G71) | G71: =IFERROR(LEFT(RIGHT(H71,LEN(H71)-32),LEN(RIGHT(H71,LEN(H71)-32))-17),"")
B72: 6 | C72: =B72&E72 -> 6Struc | D72: NOUN + IS/ARE TOO + ADJ /Cái gì đó quá…/ | E72: Struc | F72: =IF(G72="","","https://docs.google.com/uc?export=download&id="&G72) | G72: =IFERROR(LEFT(RIGHT(H72,LEN(H72)-32),LEN(RIGHT(H72,LEN(H72)-32))-17),"")
B73: 6.1 | C73: =B73&E73 -> 6.1Viet | D73: Cuốn sách này quá đắt. | E73: Viet | F73: =IF(G73="","","https://docs.google.com/uc?export=download&id="&G73) | G73: =IFERROR(LEFT(RIGHT(H73,LEN(H73)-32),LEN(RIGHT(H73,LEN(H73)-32))-17),"")
A74: 22 | B74: =B73 -> 6.1 | C74: =B74&E74 -> 6.1Eng | D74: This book is too expensive. | E74: Eng | F74: =IF(G74="","","https://docs.google.com/uc?export=download&id="&G74) -> https://docs.google.com/uc?export=download&id=1Mo0zNJRm852tNM5nRP9CNLeiZpLpam3R | G74: =IFERROR(LEFT(RIGHT(H74,LEN(H74)-32),LEN(RIGHT(H74,LEN(H74)-32))-17),"") -> 1Mo0zNJRm852tNM5nRP9CNLeiZpLpam3R | H74: https://drive.google.com/file/d/1Mo0zNJRm852tNM5nRP9CNLeiZpLpam3R/view?usp=sharing
B75: =B74 -> 6.1 | C75: =B75&E75 -> 6.1Phon | D75: ðɪs bʊk ɪz tu: ɪkˈspɛnsɪv | E75: Phon | F75: =IF(G75="","","https://docs.google.com/uc?export=download&id="&G75) | G75: =IFERROR(LEFT(RIGHT(H75,LEN(H75)-32),LEN(RIGHT(H75,LEN(H75)-32))-17),"")
B76: 6.2 | C76: =B76&E76 -> 6.2Viet | D76: Cái quần jean này quá phải chăng/hợp lý. | E76: Viet | F76: =IF(G76="","","https://docs.google.com/uc?export=download&id="&G76) | G76: =IFERROR(LEFT(RIGHT(H76,LEN(H76)-32),LEN(RIGHT(H76,LEN(H76)-32))-17),"")
A77: 23 | B77: =B76 -> 6.2 | C77: =B77&E77 -> 6.2Eng | D77: These jeans are reasonable. | E77: Eng | F77: =IF(G77="","","https://docs.google.com/uc?export=download&id="&G77) -> https://docs.google.com/uc?export=download&id=1IZkvLYOQrxn8mPfjSOWbYV2rRsDm0WZA | G77: =IFERROR(LEFT(RIGHT(H77,LEN(H77)-32),LEN(RIGHT(H77,LEN(H77)-32))-17),"") -> 1IZkvLYOQrxn8mPfjSOWbYV2rRsDm0WZA | H77: https://drive.google.com/file/d/1IZkvLYOQrxn8mPfjSOWbYV2rRsDm0WZA/view?usp=sharing
B78: =B77 -> 6.2 | C78: =B78&E78 -> 6.2Phon | D78: ði:z ʤi:nz a:r ˈri:zənəbəl | E78: Phon | F78: =IF(G78="","","https://docs.google.com/uc?export=download&id="&G78) | G78: =IFERROR(LEFT(RIGHT(H78,LEN(H78)-32),LEN(RIGHT(H78,LEN(H78)-32))-17),"")
B79: 6.3 | C79: =B79&E79 -> 6.3Viet | D79: Mặt hàng này quá đắt. | E79: Viet | F79: =IF(G79="","","https://docs.google.com/uc?export=download&id="&G79) | G79: =IFERROR(LEFT(RIGHT(H79,LEN(H79)-32),LEN(RIGHT(H79,LEN(H79)-32))-17),"")
A80: 24 | B80: =B79 -> 6.3 | C80: =B80&E80 -> 6.3Eng | D80: This item is too expensive. | E80: Eng | F80: =IF(G80="","","https://docs.google.com/uc?export=download&id="&G80) -> https://docs.google.com/uc?export=download&id=1UHT-x4TA2AQo9Wncr34Y-JvUXiANr8W_ | G80: =IFERROR(LEFT(RIGHT(H80,LEN(H80)-32),LEN(RIGHT(H80,LEN(H80)-32))-17),"") -> 1UHT-x4TA2AQo9Wncr34Y-JvUXiANr8W_ | H80: https://drive.google.com/file/d/1UHT-x4TA2AQo9Wncr34Y-JvUXiANr8W_/view?usp=sharing
B81: =B80 -> 6.3 | C81: =B81&E81 -> 6.3Phon | D81: ðɪs ˈaɪtəm ɪz tu: ɪkˈspɛnsɪv | E81: Phon | F81: =IF(G81="","","https://docs.google.com/uc?export=download&id="&G81) | G81: =IFERROR(LEFT(RIGHT(H81,LEN(H81)-32),LEN(RIGHT(H81,LEN(H81)-32))-17),"")
B82: 6.4 | C82: =B82&E82 -> 6.4Viet | D82: Sản phẩm này quá rẻ. | E82: Viet | F82: =IF(G82="","","https://docs.google.com/uc?export=download&id="&G82) | G82: =IFERROR(LEFT(RIGHT(H82,LEN(H82)-32),LEN(RIGHT(H82,LEN(H82)-32))-17),"")
A83: 25 | B83: =B82 -> 6.4 | C83: =B83&E83 -> 6.4Eng | D83: This product is too cheap. | E83: Eng | F83: =IF(G83="","","https://docs.google.com/uc?export=download&id="&G83) -> https://docs.google.com/uc?export=download&id=1-vC7fXssGUwpj1VGicfyefYgoAsEmJdW | G83: =IFERROR(LEFT(RIGHT(H83,LEN(H83)-32),LEN(RIGHT(H83,LEN(H83)-32))-17),"") -> 1-vC7fXssGUwpj1VGicfyefYgoAsEmJdW | H83: https://drive.google.com/file/d/1-vC7fXssGUwpj1VGicfyefYgoAsEmJdW/view?usp=sharing
B84: =B83 -> 6.4 | C84: =B84&E84 -> 6.4Phon | D84: ðɪs ˈpra:dʌkt ɪz tu: ʧi:p | E84: Phon | F84: =IF(G84="","","https://docs.google.com/uc?export=download&id="&G84) | G84: =IFERROR(LEFT(RIGHT(H84,LEN(H84)-32),LEN(RIGHT(H84,LEN(H84)-32))-17),"")
B85: 7 | C85: =B85&E85 -> 7Struc | D85: HOW MUCH DO/DOES + NOUN COST? /Giá bao nhiêu?/ | E85: Struc | F85: =IF(G85="","","https://docs.google.com/uc?export=download&id="&G85) | G85: =IFERROR(LEFT(RIGHT(H85,LEN(H85)-32),LEN(RIGHT(H85,LEN(H85)-32))-17),"")
B86: 7.1 | C86: =B86&E86 -> 7.1Viet | D86: Cái máy tính này giá bao nhiêu? | E86: Viet | F86: =IF(G86="","","https://docs.google.com/uc?export=download&id="&G86) | G86: =IFERROR(LEFT(RIGHT(H86,LEN(H86)-32),LEN(RIGHT(H86,LEN(H86)-32))-17),"")
A87: 26 | B87: =B86 -> 7.1 | C87: =B87&E87 -> 7.1Eng | D87: How much does this computer cost? | E87: Eng | F87: =IF(G87="","","https://docs.google.com/uc?export=download&id="&G87) -> https://docs.google.com/uc?export=download&id=17m7nkXyoI_t1qH8PoaLcdb5zWVkN_it3 | G87: =IFERROR(LEFT(RIGHT(H87,LEN(H87)-32),LEN(RIGHT(H87,LEN(H87)-32))-17),"") -> 17m7nkXyoI_t1qH8PoaLcdb5zWVkN_it3 | H87: https://drive.google.com/file/d/17m7nkXyoI_t1qH8PoaLcdb5zWVkN_it3/view?usp=sharing
B88: =B87 -> 7.1 | C88: =B88&E88 -> 7.1Phon | D88: haʊ mʌʧ dʌz ðɪs kəmˈpju:tər ka:st | E88: Phon | F88: =IF(G88="","","https://docs.google.com/uc?export=download&id="&G88) | G88: =IFERROR(LEFT(RIGHT(H88,LEN(H88)-32),LEN(RIGHT(H88,LEN(H88)-32))-17),"")
B89: 7.2 | C89: =B89&E89 -> 7.2Viet | D89: Cái ấm nước này giá bao nhiêu? | E89: Viet | F89: =IF(G89="","","https://docs.google.com/uc?export=download&id="&G89) | G89: =IFERROR(LEFT(RIGHT(H89,LEN(H89)-32),LEN(RIGHT(H89,LEN(H89)-32))-17),"")
A90: 27 | B90: =B89 -> 7.2 | C90: =B90&E90 -> 7.2Eng | D90: How much does this kettle cost? | E90: Eng | F90: =IF(G90="","","https://docs.google.com/uc?export=download&id="&G90) -> https://docs.google.com/uc?export=download&id=1Xp86zRg2xZ_CzPy4JZbyUQJsDq7ZETUG | G90: =IFERROR(LEFT(RIGHT(H90,LEN(H90)-32),LEN(RIGHT(H90,LEN(H90)-32))-17),"") -> 1Xp86zRg2xZ_CzPy4JZbyUQJsDq7ZETUG | H90: https://drive.google.com/file/d/1Xp86zRg2xZ_CzPy4JZbyUQJsDq7ZETUG/view?usp=sharing
B91: =B90 -> 7.2 | C91: =B91&E91 -> 7.2Phon | D91: haʊ mʌʧ dʌz ðɪs ˈkɛtəl ka:st | E91: Phon | F91: =IF(G91="","","https://docs.google.com/uc?export=download&id="&G91) | G91: =IFERROR(LEFT(RIGHT(H91,LEN(H91)-32),LEN(RIGHT(H91,LEN(H91)-32))-17),"")
B92: 7.3 | C92: =B92&E92 -> 7.3Viet | D92: Mấy cái áo khoác này giá bao nhiêu? | E92: Viet | F92: =IF(G92="","","https://docs.google.com/uc?export=download&id="&G92) | G92: =IFERROR(LEFT(RIGHT(H92,LEN(H92)-32),LEN(RIGHT(H92,LEN(H92)-32))-17),"")
A93: 28 | B93: =B92 -> 7.3 | C93: =B93&E93 -> 7.3Eng | D93: How much do these coats cost? | E93: Eng | F93: =IF(G93="","","https://docs.google.com/uc?export=download&id="&G93) -> https://docs.google.com/uc?export=download&id=1xYkl6BmYyyHLEjG3ozt4idvgohksTmrQ | G93: =IFERROR(LEFT(RIGHT(H93,LEN(H93)-32),LEN(RIGHT(H93,LEN(H93)-32))-17),"") -> 1xYkl6BmYyyHLEjG3ozt4idvgohksTmrQ | H93: https://drive.google.com/file/d/1xYkl6BmYyyHLEjG3ozt4idvgohksTmrQ/view?usp=sharing
B94: =B93 -> 7.3 | C94: =B94&E94 -> 7.3Phon | D94: haʊ mʌʧ du: ði:z koʊts ka:st | E94: Phon | F94: =IF(G94="","","https://docs.google.com/uc?export=download&id="&G94) | G94: =IFERROR(LEFT(RIGHT(H94,LEN(H94)-32),LEN(RIGHT(H94,LEN(H94)-32))-17),"")
B95: 7.4 | C95: =B95&E95 -> 7.4Viet | D95: Lọ nước hoa này giá bao nhiêu? | E95: Viet | F95: =IF(G95="","","https://docs.google.com/uc?export=download&id="&G95) | G95: =IFERROR(LEFT(RIGHT(H95,LEN(H95)-32),LEN(RIGHT(H95,LEN(H95)-32))-17),"")
A96: 29 | B96: =B95 -> 7.4 | C96: =B96&E96 -> 7.4Eng | D96: How much does this bottle of perfume? | E96: Eng | F96: =IF(G96="","","https://docs.google.com/uc?export=download&id="&G96) -> https://docs.google.com/uc?export=download&id=1w4SZPfzZDp9BR2WZqAfRLPBs1sgr2ByW | G96: =IFERROR(LEFT(RIGHT(H96,LEN(H96)-32),LEN(RIGHT(H96,LEN(H96)-32))-17),"") -> 1w4SZPfzZDp9BR2WZqAfRLPBs1sgr2ByW | H96: https://drive.google.com/file/d/1w4SZPfzZDp9BR2WZqAfRLPBs1sgr2ByW/view?usp=sharing
B97: =B96 -> 7.4 | C97: =B97&E97 -> 7.4Phon | D97: haʊ mʌʧ dʌz ðɪs ˈba:təl ʌv pərˈfjuːm | E97: Phon | F97: =IF(G97="","","https://docs.google.com/uc?export=download&id="&G97) | G97: =IFERROR(LEFT(RIGHT(H97,LEN(H97)-32),LEN(RIGHT(H97,LEN(H97)-32))-17),"")
B98: 7.5 | C98: =B98&E98 -> 7.5Viet | D98: Đôi giày này giá bao nhiêu? | E98: Viet | F98: =IF(G98="","","https://docs.google.com/uc?export=download&id="&G98) | G98: =IFERROR(LEFT(RIGHT(H98,LEN(H98)-32),LEN(RIGHT(H98,LEN(H98)-32))-17),"")
A99: 30 | B99: =B98 -> 7.5 | C99: =B99&E99 -> 7.5Eng | D99: How much does this pair of shoes? | E99: Eng | F99: =IF(G99="","","https://docs.google.com/uc?export=download&id="&G99) -> https://docs.google.com/uc?export=download&id=1ogGPQCk1_isKB7tR3IRyp9ATY-ili1nM | G99: =IFERROR(LEFT(RIGHT(H99,LEN(H99)-32),LEN(RIGHT(H99,LEN(H99)-32))-17),"") -> 1ogGPQCk1_isKB7tR3IRyp9ATY-ili1nM | H99: https://drive.google.com/file/d/1ogGPQCk1_isKB7tR3IRyp9ATY-ili1nM/view?usp=sharing
B100: =B99 -> 7.5 | C100: =B100&E100 -> 7.5Phon | D100: haʊ mʌʧ dʌz ðɪs pɛr ʌv ʃu:z | E100: Phon | F100: =IF(G100="","","https://docs.google.com/uc?export=download&id="&G100) | G100: =IFERROR(LEFT(RIGHT(H100,LEN(H100)-32),LEN(RIGHT(H100,LEN(H100)-32))-17),"")
B101: 7.6 | C101: =B101&E101 -> 7.6Viet | D101: Ly cà phê này giá bao nhiêu? | E101: Viet | F101: =IF(G101="","","https://docs.google.com/uc?export=download&id="&G101) | G101: =IFERROR(LEFT(RIGHT(H101,LEN(H101)-32),LEN(RIGHT(H101,LEN(H101)-32))-17),"")
...

Sheet Viet
B2: Sentence | C2: Link | D2: ID | E2: Copy Google drive to …
B3: 01-05 | C3: =IF(D3="","","https://docs.google.com/uc?export=download&id="&D3) -> https://docs.google.com/uc?export=download&id=16UItxbRFXQsHC6JqNryXRfu_CMxio5BD | D3: =IFERROR(LEFT(RIGHT(E3,LEN(E3)-32),LEN(RIGHT(E3,LEN(E3)-32))-17),"") -> 16UItxbRFXQsHC6JqNryXRfu_CMxio5BD | E3: https://drive.google.com/file/d/16UItxbRFXQsHC6JqNryXRfu_CMxio5BD/view?usp=sharing
B4: 06-10 | C4: =IF(D4="","","https://docs.google.com/uc?export=download&id="&D4) -> https://docs.google.com/uc?export=download&id=1tqASmv37J5zMRAaCyySLAl2omzPg-vbY | D4: =IFERROR(LEFT(RIGHT(E4,LEN(E4)-32),LEN(RIGHT(E4,LEN(E4)-32))-17),"") -> 1tqASmv37J5zMRAaCyySLAl2omzPg-vbY | E4: https://drive.google.com/file/d/1tqASmv37J5zMRAaCyySLAl2omzPg-vbY/view?usp=sharing
B5: 11-15 | C5: =IF(D5="","","https://docs.google.com/uc?export=download&id="&D5) -> https://docs.google.com/uc?export=download&id=1zu8BmU5AsbyFTurAxfEUJog2JD12PCcj | D5: =IFERROR(LEFT(RIGHT(E5,LEN(E5)-32),LEN(RIGHT(E5,LEN(E5)-32))-17),"") -> 1zu8BmU5AsbyFTurAxfEUJog2JD12PCcj | E5: https://drive.google.com/file/d/1zu8BmU5AsbyFTurAxfEUJog2JD12PCcj/view?usp=sharing
B6: 16-20 | C6: =IF(D6="","","https://docs.google.com/uc?export=download&id="&D6) -> https://docs.google.com/uc?export=download&id=19ReWTE3nbR5jjo8wYUX4QIpAZOw_rnNA | D6: =IFERROR(LEFT(RIGHT(E6,LEN(E6)-32),LEN(RIGHT(E6,LEN(E6)-32))-17),"") -> 19ReWTE3nbR5jjo8wYUX4QIpAZOw_rnNA | E6: https://drive.google.com/file/d/19ReWTE3nbR5jjo8wYUX4QIpAZOw_rnNA/view?usp=sharing
B7: 21-25 | C7: =IF(D7="","","https://docs.google.com/uc?export=download&id="&D7) -> https://docs.google.com/uc?export=download&id=1vZIwkXnA5xCUT3PRPjEXdiVcqQGsAEh8 | D7: =IFERROR(LEFT(RIGHT(E7,LEN(E7)-32),LEN(RIGHT(E7,LEN(E7)-32))-17),"") -> 1vZIwkXnA5xCUT3PRPjEXdiVcqQGsAEh8 | E7: https://drive.google.com/file/d/1vZIwkXnA5xCUT3PRPjEXdiVcqQGsAEh8/view?usp=sharing
B8: 26-30 | C8: =IF(D8="","","https://docs.google.com/uc?export=download&id="&D8) -> https://docs.google.com/uc?export=download&id=1Prr7EGqLz05h6XYDbwD3L2N6zUx-x7jO | D8: =IFERROR(LEFT(RIGHT(E8,LEN(E8)-32),LEN(RIGHT(E8,LEN(E8)-32))-17),"") -> 1Prr7EGqLz05h6XYDbwD3L2N6zUx-x7jO | E8: https://drive.google.com/file/d/1Prr7EGqLz05h6XYDbwD3L2N6zUx-x7jO/view?usp=sharing
B9: 31-34 | C9: =IF(D9="","","https://docs.google.com/uc?export=download&id="&D9) -> https://docs.google.com/uc?export=download&id=1DRzFbHlLN_HTeLrEHTYWI7X7-nsRDN9F | D9: =IFERROR(LEFT(RIGHT(E9,LEN(E9)-32),LEN(RIGHT(E9,LEN(E9)-32))-17),"") -> 1DRzFbHlLN_HTeLrEHTYWI7X7-nsRDN9F | E9: https://drive.google.com/file/d/1DRzFbHlLN_HTeLrEHTYWI7X7-nsRDN9F/view?usp=sharing
B10: 01-34 | C10: =IF(D10="","","https://docs.google.com/uc?export=download&id="&D10) -> https://docs.google.com/uc?export=download&id=1RHvj1ANg1BAYXqvKADUtV9HWVai_93Ex | D10: =IFERROR(LEFT(RIGHT(E10,LEN(E10)-32),LEN(RIGHT(E10,LEN(E10)-32))-17),"") -> 1RHvj1ANg1BAYXqvKADUtV9HWVai_93Ex | E10: https://drive.google.com/file/d/1RHvj1ANg1BAYXqvKADUtV9HWVai_93Ex/view?usp=sharing
C11: =IF(D11="","","https://docs.google.com/uc?export=download&id="&D11) | D11: =IFERROR(LEFT(RIGHT(E11,LEN(E11)-32),LEN(RIGHT(E11,LEN(E11)-32))-17),"")
C12: =IF(D12="","","https://docs.google.com/uc?export=download&id="&D12) | D12: =IFERROR(LEFT(RIGHT(E12,LEN(E12)-32),LEN(RIGHT(E12,LEN(E12)-32))-17),"")
C13: =IF(D13="","","https://docs.google.com/uc?export=download&id="&D13&"""") | D13: =IFERROR(LEFT(RIGHT(E13,LEN(E13)-32),LEN(RIGHT(E13,LEN(E13)-32))-17),"")

Sheet Sum
B2: Sentence | C2: Link | D2: ID | E2: Copy Google drive to …
B3: Woman | C3: =IF(D3="","","https://docs.google.com/uc?export=download&id="&D3) -> https://docs.google.com/uc?export=download&id=1Sxauxdmjchkj8TyASYJCj9mTOL5PSzWr | D3: =IFERROR(LEFT(RIGHT(E3,LEN(E3)-32),LEN(RIGHT(E3,LEN(E3)-32))-17),"") -> 1Sxauxdmjchkj8TyASYJCj9mTOL5PSzWr | E3: https://drive.google.com/file/d/1Sxauxdmjchkj8TyASYJCj9mTOL5PSzWr/view?usp=sharing
B4: Man | C4: =IF(D4="","","https://docs.google.com/uc?export=download&id="&D4) -> https://docs.google.com/uc?export=download&id=1TQKwAZuLCUmzvKorNgRFEptFrh9sF2Ko | D4: =IFERROR(LEFT(RIGHT(E4,LEN(E4)-32),LEN(RIGHT(E4,LEN(E4)-32))-17),"") -> 1TQKwAZuLCUmzvKorNgRFEptFrh9sF2Ko | E4: https://drive.google.com/file/d/1TQKwAZuLCUmzvKorNgRFEptFrh9sF2Ko/view?usp=sharing

Sheet Ramdom
B1: From | C1: 126
B2: To | C2: 139
C3: No | D3: No | E3: Viet | F3: Eng
A4: =C1 -> 126 | B4: =IF(A4="","",RANDBETWEEN($C$1,$C$2)) -> 138 | C4: =IFERROR($C$1-1+_xlfn.RANK.EQ(B4,$B$4:$B$142)+COUNTIF(B$4:$B4,B4)-1,"") -> 128 | D4: =IFERROR(VLOOKUP(C4,Shopping!A:B,2,0),"") -> 31.3 | E4: =IFERROR(VLOOKUP(D4&"Viet",Shopping!C:D,2,0),"") -> Tôi muốn mua 3 món. | F4: =IFERROR(VLOOKUP(D4&"Eng",Shopping!C:D,2,0),"") -> I would like to get three items.
A5: =IFERROR(IF(A4+1>$C$2,"",A4+1),"") -> 127 | B5: =IF(A5="","",RANDBETWEEN($C$1,$C$2)) -> 137 | C5: =IFERROR($C$1-1+_xlfn.RANK.EQ(B5,$B$4:$B$242)+COUNTIF(B$4:$B5,B5)-1,"") -> 129 | D5: =IFERROR(VLOOKUP(C5,Shopping!A:B,2,0),"") -> 31.4 | E5: =IFERROR(VLOOKUP(D5&"Viet",Shopping!C:D,2,0),"") -> Tôi muốn mua 1 túi 5 kí gạo. | F5: =IFERROR(VLOOKUP(D5&"Eng",Shopping!C:D,2,0),"") -> I would like a 5-kilogram bag of rice.
A6: =IFERROR(IF(A5+1>$C$2,"",A5+1),"") -> 128 | B6: =IF(A6="","",RANDBETWEEN($C$1,$C$2)) -> 133 | C6: =IFERROR($C$1-1+_xlfn.RANK.EQ(B6,$B$4:$B$242)+COUNTIF(B$4:$B6,B6)-1,"") -> 132 | D6: =IFERROR(VLOOKUP(C6,Shopping!A:B,2,0),"") -> 32.3 | E6: =IFERROR(VLOOKUP(D6&"Viet",Shopping!C:D,2,0),"") -> Khi nào thì kem chống nắng này hết hạn? | F6: =IFERROR(VLOOKUP(D6&"Eng",Shopping!C:D,2,0),"") -> When does this sunscreen expire?
A7: =IFERROR(IF(A6+1>$C$2,"",A6+1),"") -> 129 | B7: =IF(A7="","",RANDBETWEEN($C$1,$C$2)) -> 130 | C7: =IFERROR($C$1-1+_xlfn.RANK.EQ(B7,$B$4:$B$242)+COUNTIF(B$4:$B7,B7)-1,"") -> 135 | D7: =IFERROR(VLOOKUP(C7,Shopping!A:B,2,0),"") -> 33.2 | E7: =IFERROR(VLOOKUP(D7&"Viet",Shopping!C:D,2,0),"") -> Không biết cô có cái áo len này cùng kiểu mà chất liệu khác không? | F7: =IFERROR(VLOOKUP(D7&"Eng",Shopping!C:D,2,0),"") -> I was wondering if you had the same style of sweater made from another fabric.
A8: =IFERROR(IF(A7+1>$C$2,"",A7+1),"") -> 130 | B8: =IF(A8="","",RANDBETWEEN($C$1,$C$2)) -> 134 | C8: =IFERROR($C$1-1+_xlfn.RANK.EQ(B8,$B$4:$B$242)+COUNTIF(B$4:$B8,B8)-1,"") -> 130 | D8: =IFERROR(VLOOKUP(C8,Shopping!A:B,2,0),"") -> 32.1 | E8: =IFERROR(VLOOKUP(D8&"Viet",Shopping!C:D,2,0),"") -> Thịt heo này khi nào hết hạn? | F8: =IFERROR(VLOOKUP(D8&"Eng",Shopping!C:D,2,0),"") -> When does this pork expire?
A9: =IFERROR(IF(A8+1>$C$2,"",A8+1),"") -> 131 | B9: =IF(A9="","",RANDBETWEEN($C$1,$C$2)) -> 139 | C9: =IFERROR($C$1-1+_xlfn.RANK.EQ(B9,$B$4:$B$242)+COUNTIF(B$4:$B9,B9)-1,"") -> 126 | D9: =IFERROR(VLOOKUP(C9,Shopping!A:B,2,0),"") -> 31.1 | E9: =IFERROR(VLOOKUP(D9&"Viet",Shopping!C:D,2,0),"") -> Tôi muốn mua 1 lít sữa. | F9: =IFERROR(VLOOKUP(D9&"Eng",Shopping!C:D,2,0),"") -> I would like a liter of milk.
A10: =IFERROR(IF(A9+1>$C$2,"",A9+1),"") -> 132 | B10: =IF(A10="","",RANDBETWEEN($C$1,$C$2)) -> 128 | C10: =IFERROR($C$1-1+_xlfn.RANK.EQ(B10,$B$4:$B$242)+COUNTIF(B$4:$B10,B10)-1,"") -> 137 | D10: =IFERROR(VLOOKUP(C10,Shopping!A:B,2,0),"") -> 34.1 | E10: =IFERROR(VLOOKUP(D10&"Viet",Shopping!C:D,2,0),"") -> Tôi thích quần áo hơi rộng một chút. | F10: =IFERROR(VLOOKUP(D10&"Eng",Shopping!C:D,2,0),"") -> I prefer my clothes to be a little loose.
A11: =IFERROR(IF(A10+1>$C$2,"",A10+1),"") -> 133 | B11: =IF(A11="","",RANDBETWEEN($C$1,$C$2)) -> 134 | C11: =IFERROR($C$1-1+_xlfn.RANK.EQ(B11,$B$4:$B$242)+COUNTIF(B$4:$B11,B11)-1,"") -> 131 | D11: =IFERROR(VLOOKUP(C11,Shopping!A:B,2,0),"") -> 32.2 | E11: =IFERROR(VLOOKUP(D11&"Viet",Shopping!C:D,2,0),"") -> Khi nào sô cô la này hết hạn? | F11: =IFERROR(VLOOKUP(D11&"Eng",Shopping!C:D,2,0),"") -> When does this chocolate expire?
A12: =IFERROR(IF(A11+1>$C$2,"",A11+1),"") -> 134 | B12: =IF(A12="","",RANDBETWEEN($C$1,$C$2)) -> 139 | C12: =IFERROR($C$1-1+_xlfn.RANK.EQ(B12,$B$4:$B$242)+COUNTIF(B$4:$B12,B12)-1,"") -> 127 | D12: =IFERROR(VLOOKUP(C12,Shopping!A:B,2,0),"") -> 31.2 | E12: =IFERROR(VLOOKUP(D12&"Viet",Shopping!C:D,2,0),"") -> Tôi muốn mua 2 kí thịt bò. | F12: =IFERROR(VLOOKUP(D12&"Eng",Shopping!C:D,2,0),"") -> I would like 2 kilos of beef.
A13: =IFERROR(IF(A12+1>$C$2,"",A12+1),"") -> 135 | B13: =IF(A13="","",RANDBETWEEN($C$1,$C$2)) -> 128 | C13: =IFERROR($C$1-1+_xlfn.RANK.EQ(B13,$B$4:$B$242)+COUNTIF(B$4:$B13,B13)-1,"") -> 138 | D13: =IFERROR(VLOOKUP(C13,Shopping!A:B,2,0),"") -> 34.2 | E13: =IFERROR(VLOOKUP(D13&"Viet",Shopping!C:D,2,0),"") -> Tôi thích quần áo rộng rãi. | F13: =IFERROR(VLOOKUP(D13&"Eng",Shopping!C:D,2,0),"") -> I prefer my clothes to be baggy.
A14: =IFERROR(IF(A13+1>$C$2,"",A13+1),"") -> 136 | B14: =IF(A14="","",RANDBETWEEN($C$1,$C$2)) -> 133 | C14: =IFERROR($C$1-1+_xlfn.RANK.EQ(B14,$B$4:$B$242)+COUNTIF(B$4:$B14,B14)-1,"") -> 133 | D14: =IFERROR(VLOOKUP(C14,Shopping!A:B,2,0),"") -> 32.4 | E14: =IFERROR(VLOOKUP(D14&"Viet",Shopping!C:D,2,0),"") -> Khi nào mật ong này hết hạn? | F14: =IFERROR(VLOOKUP(D14&"Eng",Shopping!C:D,2,0),"") -> When does this honey expire?
A15: =IFERROR(IF(A14+1>$C$2,"",A14+1),"") -> 137 | B15: =IF(A15="","",RANDBETWEEN($C$1,$C$2)) -> 133 | C15: =IFERROR($C$1-1+_xlfn.RANK.EQ(B15,$B$4:$B$242)+COUNTIF(B$4:$B15,B15)-1,"") -> 134 | D15: =IFERROR(VLOOKUP(C15,Shopping!A:B,2,0),"") -> 33.1 | E15: =IFERROR(VLOOKUP(D15&"Viet",Shopping!C:D,2,0),"") -> Không biết cô có chiếc áo len này cỡ lớn hơn không? | F15: =IFERROR(VLOOKUP(D15&"Eng",Shopping!C:D,2,0),"") -> I was wondering if you had this sweater in a larger size.
A16: =IFERROR(IF(A15+1>$C$2,"",A15+1),"") -> 138 | B16: =IF(A16="","",RANDBETWEEN($C$1,$C$2)) -> 126 | C16: =IFERROR($C$1-1+_xlfn.RANK.EQ(B16,$B$4:$B$242)+COUNTIF(B$4:$B16,B16)-1,"") -> 139 | D16: =IFERROR(VLOOKUP(C16,Shopping!A:B,2,0),"") -> 34.3 | E16: =IFERROR(VLOOKUP(D16&"Viet",Shopping!C:D,2,0),"") -> Tôi thích quần áo thời trang xíu. | F16: =IFERROR(VLOOKUP(D16&"Eng",Shopping!C:D,2,0),"") -> I prefer my clothes to be fashionable. | J16: ll;
A17: =IFERROR(IF(A16+1>$C$2,"",A16+1),"") -> 139 | B17: =IF(A17="","",RANDBETWEEN($C$1,$C$2)) -> 129 | C17: =IFERROR($C$1-1+_xlfn.RANK.EQ(B17,$B$4:$B$242)+COUNTIF(B$4:$B17,B17)-1,"") -> 136 | D17: =IFERROR(VLOOKUP(C17,Shopping!A:B,2,0),"") -> 33.3 | E17: =IFERROR(VLOOKUP(D17&"Viet",Shopping!C:D,2,0),"") -> Không biết cô có cái nào khác mà không bị lỗi không? | F17: =IFERROR(VLOOKUP(D17&"Eng",Shopping!C:D,2,0),"") -> I was wondering if you had another one that is not damaged.
A18: =IFERROR(IF(A17+1>$C$2,"",A17+1),"") | B18: =IF(A18="","",RANDBETWEEN($C$1,$C$2)) | C18: =IFERROR($C$1-1+_xlfn.RANK.EQ(B18,$B$4:$B$242)+COUNTIF(B$4:$B18,B18)-1,"") | D18: =IFERROR(VLOOKUP(C18,Shopping!A:B,2,0),"") | E18: =IFERROR(VLOOKUP(D18&"Viet",Shopping!C:D,2,0),"") | F18: =IFERROR(VLOOKUP(D18&"Eng",Shopping!C:D,2,0),"")
A19: =IFERROR(IF(A18+1>$C$2,"",A18+1),"") | B19: =IF(A19="","",RANDBETWEEN($C$1,$C$2)) | C19: =IFERROR($C$1-1+_xlfn.RANK.EQ(B19,$B$4:$B$242)+COUNTIF(B$4:$B19,B19)-1,"") | D19: =IFERROR(VLOOKUP(C19,Shopping!A:B,2,0),"") | E19: =IFERROR(VLOOKUP(D19&"Viet",Shopping!C:D,2,0),"") | F19: =IFERROR(VLOOKUP(D19&"Eng",Shopping!C:D,2,0),"") | J19: 4
A20: =IFERROR(IF(A19+1>$C$2,"",A19+1),"") | B20: =IF(A20="","",RANDBETWEEN($C$1,$C$2)) | C20: =IFERROR($C$1-1+_xlfn.RANK.EQ(B20,$B$4:$B$242)+COUNTIF(B$4:$B20,B20)-1,"") | D20: =IFERROR(VLOOKUP(C20,Shopping!A:B,2,0),"") | E20: =IFERROR(VLOOKUP(D20&"Viet",Shopping!C:D,2,0),"") | F20: =IFERROR(VLOOKUP(D20&"Eng",Shopping!C:D,2,0),"")
A21: =IFERROR(IF(A20+1>$C$2,"",A20+1),"") | B21: =IF(A21="","",RANDBETWEEN($C$1,$C$2)) | C21: =IFERROR($C$1-1+_xlfn.RANK.EQ(B21,$B$4:$B$242)+COUNTIF(B$4:$B21,B21)-1,"") | D21: =IFERROR(VLOOKUP(C21,Shopping!A:B,2,0),"") | E21: =IFERROR(VLOOKUP(D21&"Viet",Shopping!C:D,2,0),"") | F21: =IFERROR(VLOOKUP(D21&"Eng",Shopping!C:D,2,0),"")
A22: =IFERROR(IF(A21+1>$C$2,"",A21+1),"") | B22: =IF(A22="","",RANDBETWEEN($C$1,$C$2)) | C22: =IFERROR($C$1-1+_xlfn.RANK.EQ(B22,$B$4:$B$242)+COUNTIF(B$4:$B22,B22)-1,"") | D22: =IFERROR(VLOOKUP(C22,Shopping!A:B,2,0),"") | E22: =IFERROR(VLOOKUP(D22&"Viet",Shopping!C:D,2,0),"") | F22: =IFERROR(VLOOKUP(D22&"Eng",Shopping!C:D,2,0),"")
A23: =IFERROR(IF(A22+1>$C$2,"",A22+1),"") | B23: =IF(A23="","",RANDBETWEEN($C$1,$C$2)) | C23: =IFERROR($C$1-1+_xlfn.RANK.EQ(B23,$B$4:$B$242)+COUNTIF(B$4:$B23,B23)-1,"") | D23: =IFERROR(VLOOKUP(C23,Shopping!A:B,2,0),"") | E23: =IFERROR(VLOOKUP(D23&"Viet",Shopping!C:D,2,0),"") | F23: =IFERROR(VLOOKUP(D23&"Eng",Shopping!C:D,2,0),"")
A24: =IFERROR(IF(A23+1>$C$2,"",A23+1),"") | B24: =IF(A24="","",RANDBETWEEN($C$1,$C$2)) | C24: =IFERROR($C$1-1+_xlfn.RANK.EQ(B24,$B$4:$B$242)+COUNTIF(B$4:$B24,B24)-1,"") | D24: =IFERROR(VLOOKUP(C24,Shopping!A:B,2,0),"") | E24: =IFERROR(VLOOKUP(D24&"Viet",Shopping!C:D,2,0),"") | F24: =IFERROR(VLOOKUP(D24&"Eng",Shopping!C:D,2,0),"")
A25: =IFERROR(IF(A24+1>$C$2,"",A24+1),"") | B25: =IF(A25="","",RANDBETWEEN($C$1,$C$2)) | C25: =IFERROR($C$1-1+_xlfn.RANK.EQ(B25,$B$4:$B$242)+COUNTIF(B$4:$B25,B25)-1,"") | D25: =IFERROR(VLOOKUP(C25,Shopping!A:B,2,0),"") | E25: =IFERROR(VLOOKUP(D25&"Viet",Shopping!C:D,2,0),"") | F25: =IFERROR(VLOOKUP(D25&"Eng",Shopping!C:D,2,0),"")
A26: =IFERROR(IF(A25+1>$C$2,"",A25+1),"") | B26: =IF(A26="","",RANDBETWEEN($C$1,$C$2)) | C26: =IFERROR($C$1-1+_xlfn.RANK.EQ(B26,$B$4:$B$242)+COUNTIF(B$4:$B26,B26)-1,"") | D26: =IFERROR(VLOOKUP(C26,Shopping!A:B,2,0),"") | E26: =IFERROR(VLOOKUP(D26&"Viet",Shopping!C:D,2,0),"") | F26: =IFERROR(VLOOKUP(D26&"Eng",Shopping!C:D,2,0),"")
A27: =IFERROR(IF(A26+1>$C$2,"",A26+1),"") | B27: =IF(A27="","",RANDBETWEEN($C$1,$C$2)) | C27: =IFERROR($C$1-1+_xlfn.RANK.EQ(B27,$B$4:$B$242)+COUNTIF(B$4:$B27,B27)-1,"") | D27: =IFERROR(VLOOKUP(C27,Shopping!A:B,2,0),"") | E27: =IFERROR(VLOOKUP(D27&"Viet",Shopping!C:D,2,0),"") | F27: =IFERROR(VLOOKUP(D27&"Eng",Shopping!C:D,2,0),"")
A28: =IFERROR(IF(A27+1>$C$2,"",A27+1),"") | B28: =IF(A28="","",RANDBETWEEN($C$1,$C$2)) | C28: =IFERROR($C$1-1+_xlfn.RANK.EQ(B28,$B$4:$B$242)+COUNTIF(B$4:$B28,B28)-1,"") | D28: =IFERROR(VLOOKUP(C28,Shopping!A:B,2,0),"") | E28: =IFERROR(VLOOKUP(D28&"Viet",Shopping!C:D,2,0),"") | F28: =IFERROR(VLOOKUP(D28&"Eng",Shopping!C:D,2,0),"")
A29: =IFERROR(IF(A28+1>$C$2,"",A28+1),"") | B29: =IF(A29="","",RANDBETWEEN($C$1,$C$2)) | C29: =IFERROR($C$1-1+_xlfn.RANK.EQ(B29,$B$4:$B$242)+COUNTIF(B$4:$B29,B29)-1,"") | D29: =IFERROR(VLOOKUP(C29,Shopping!A:B,2,0),"") | E29: =IFERROR(VLOOKUP(D29&"Viet",Shopping!C:D,2,0),"") | F29: =IFERROR(VLOOKUP(D29&"Eng",Shopping!C:D,2,0),"")
A30: =IFERROR(IF(A29+1>$C$2,"",A29+1),"") | B30: =IF(A30="","",RANDBETWEEN($C$1,$C$2)) | C30: =IFERROR($C$1-1+_xlfn.RANK.EQ(B30,$B$4:$B$242)+COUNTIF(B$4:$B30,B30)-1,"") | D30: =IFERROR(VLOOKUP(C30,Shopping!A:B,2,0),"") | E30: =IFERROR(VLOOKUP(D30&"Viet",Shopping!C:D,2,0),"") | F30: =IFERROR(VLOOKUP(D30&"Eng",Shopping!C:D,2,0),"")
A31: =IFERROR(IF(A30+1>$C$2,"",A30+1),"") | B31: =IF(A31="","",RANDBETWEEN($C$1,$C$2)) | C31: =IFERROR($C$1-1+_xlfn.RANK.EQ(B31,$B$4:$B$242)+COUNTIF(B$4:$B31,B31)-1,"") | D31: =IFERROR(VLOOKUP(C31,Shopping!A:B,2,0),"") | E31: =IFERROR(VLOOKUP(D31&"Viet",Shopping!C:D,2,0),"") | F31: =IFERROR(VLOOKUP(D31&"Eng",Shopping!C:D,2,0),"")
... A72: =IFERROR(IF(A71+1>$C$2,"",A71+1),"") | B72: =IF(A72="","",RANDBETWEEN($C$1,$C$2)) | C72: =IFERROR($C$1-1+_xlfn.RANK.EQ(B72,$B$4:$B$242)+COUNTIF(B$4:$B72,B72)-1,"") | D72: =IFERROR(VLOOKUP(C72,Shopping!A:B,2,0),"") | E72: =IFERROR(VLOOKUP(D72&"Viet",Shopping!C:D,2,0),"") | F72: =IFERROR(VLOOKUP(D72&"Eng",Shopping!C:D,2,0),"")
A73: =IFERROR(IF(A72+1>$C$2,"",A72+1),"") | B73: =IF(A73="","",RANDBETWEEN($C$1,$C$2)) | C73: =IFERROR($C$1-1+_xlfn.RANK.EQ(B73,$B$4:$B$242)+COUNTIF(B$4:$B73,B73)-1,"") | D73: =IFERROR(VLOOKUP(C73,Shopping!A:B,2,0),"")
A74: =IFERROR(IF(A73+1>$C$2,"",A73+1),"") | B74: =IF(A74="","",RANDBETWEEN($C$1,$C$2)) | C74: =IFERROR($C$1-1+_xlfn.RANK.EQ(B74,$B$4:$B$242)+COUNTIF(B$4:$B74,B74)-1,"") | D74: =IFERROR(VLOOKUP(C74,Shopping!A:B,2,0),"")
A75: =IFERROR(IF(A74+1>$C$2,"",A74+1),"") | B75: =IF(A75="","",RANDBETWEEN($C$1,$C$2)) | C75: =IFERROR($C$1-1+_xlfn.RANK.EQ(B75,$B$4:$B$242)+COUNTIF(B$4:$B75,B75)-1,"") | D75: =IFERROR(VLOOKUP(C75,Shopping!A:B,2,0),"")
A76: =IFERROR(IF(A75+1>$C$2,"",A75+1),"") | B76: =IF(A76="","",RANDBETWEEN($C$1,$C$2)) | C76: =IFERROR($C$1-1+_xlfn.RANK.EQ(B76,$B$4:$B$242)+COUNTIF(B$4:$B76,B76)-1,"") | D76: =IFERROR(VLOOKUP(C76,Shopping!A:B,2,0),"")
A77: =IFERROR(IF(A76+1>$C$2,"",A76+1),"") | B77: =IF(A77="","",RANDBETWEEN($C$1,$C$2)) | C77: =IFERROR($C$1-1+_xlfn.RANK.EQ(B77,$B$4:$B$242)+COUNTIF(B$4:$B77,B77)-1,"") | D77: =IFERROR(VLOOKUP(C77,Shopping!A:B,2,0),"")
A78: =IFERROR(IF(A77+1>$C$2,"",A77+1),"") | B78: =IF(A78="","",RANDBETWEEN($C$1,$C$2)) | C78: =IFERROR($C$1-1+_xlfn.RANK.EQ(B78,$B$4:$B$242)+COUNTIF(B$4:$B78,B78)-1,"") | D78: =IFERROR(VLOOKUP(C78,Shopping!A:B,2,0),"")
A79: =IFERROR(IF(A78+1>$C$2,"",A78+1),"") | B79: =IF(A79="","",RANDBETWEEN($C$1,$C$2)) | C79: =IFERROR($C$1-1+_xlfn.RANK.EQ(B79,$B$4:$B$242)+COUNTIF(B$4:$B79,B79)-1,"") | D79: =IFERROR(VLOOKUP(C79,Shopping!A:B,2,0),"")
A80: =IFERROR(IF(A79+1>$C$2,"",A79+1),"") | B80: =IF(A80="","",RANDBETWEEN($C$1,$C$2)) | C80: =IFERROR($C$1-1+_xlfn.RANK.EQ(B80,$B$4:$B$242)+COUNTIF(B$4:$B80,B80)-1,"") | D80: =IFERROR(VLOOKUP(C80,Shopping!A:B,2,0),"")
A81: =IFERROR(IF(A80+1>$C$2,"",A80+1),"") | B81: =IF(A81="","",RANDBETWEEN($C$1,$C$2)) | C81: =IFERROR($C$1-1+_xlfn.RANK.EQ(B81,$B$4:$B$242)+COUNTIF(B$4:$B81,B81)-1,"") | D81: =IFERROR(VLOOKUP(C81,Shopping!A:B,2,0),"")
A82: =IFERROR(IF(A81+1>$C$2,"",A81+1),"") | B82: =IF(A82="","",RANDBETWEEN($C$1,$C$2)) | C82: =IFERROR($C$1-1+_xlfn.RANK.EQ(B82,$B$4:$B$242)+COUNTIF(B$4:$B82,B82)-1,"") | D82: =IFERROR(VLOOKUP(C82,Shopping!A:B,2,0),"")
A83: =IFERROR(IF(A82+1>$C$2,"",A82+1),"") | B83: =IF(A83="","",RANDBETWEEN($C$1,$C$2)) | C83: =IFERROR($C$1-1+_xlfn.RANK.EQ(B83,$B$4:$B$242)+COUNTIF(B$4:$B83,B83)-1,"") | D83: =IFERROR(VLOOKUP(C83,Shopping!A:B,2,0),"")
A84: =IFERROR(IF(A83+1>$C$2,"",A83+1),"") | B84: =IF(A84="","",RANDBETWEEN($C$1,$C$2)) | C84: =IFERROR($C$1-1+_xlfn.RANK.EQ(B84,$B$4:$B$242)+COUNTIF(B$4:$B84,B84)-1,"") | D84: =IFERROR(VLOOKUP(C84,Shopping!A:B,2,0),"")
... A142: =IFERROR(IF(A141+1>$C$2,"",A141+1),"") | B142: =IF(A142="","",RANDBETWEEN($C$1,$C$2)) | C142: =IFERROR($C$1-1+_xlfn.RANK.EQ(B142,$B$4:$B$242)+COUNTIF(B$4:$B142,B142)-1,"") | D142: =IFERROR(VLOOKUP(C142,Shopping!A:B,2,0),"")
A143: =IFERROR(IF(A142+1>$C$2,"",A142+1),"") | B143: =IF(A143="","",RANDBETWEEN($C$1,$C$2))
A144: =IFERROR(IF(A143+1>$C$2,"",A143+1),"") | B144: =IF(A144="","",RANDBETWEEN($C$1,$C$2))
A145: =IFERROR(IF(A144+1>$C$2,"",A144+1),"") | B145: =IF(A145="","",RANDBETWEEN($C$1,$C$2))
A146: =IFERROR(IF(A145+1>$C$2,"",A145+1),"") | B146: =IF(A146="","",RANDBETWEEN($C$1,$C$2))
A147: =IFERROR(IF(A146+1>$C$2,"",A146+1),"") | B147: =IF(A147="","",RANDBETWEEN($C$1,$C$2))
A148: =IFERROR(IF(A147+1>$C$2,"",A147+1),"") | B148: =IF(A148="","",RANDBETWEEN($C$1,$C$2))
A149: =IFERROR(IF(A148+1>$C$2,"",A148+1),"") | B149: =IF(A149="","",RANDBETWEEN($C$1,$C$2))
A150: =IFERROR(IF(A149+1>$C$2,"",A149+1),"") | B150: =IF(A150="","",RANDBETWEEN($C$1,$C$2))
A151: =IFERROR(IF(A150+1>$C$2,"",A150+1),"") | B151: =IF(A151="","",RANDBETWEEN($C$1,$C$2))
A152: =IFERROR(IF(A151+1>$C$2,"",A151+1),"") | B152: =IF(A152="","",RANDBETWEEN($C$1,$C$2))
A153: =IFERROR(IF(A152+1>$C$2,"",A152+1),"") | B153: =IF(A153="","",RANDBETWEEN($C$1,$C$2))
A154: =IFERROR(IF(A153+1>$C$2,"",A153+1),"") | B154: =IF(A154="","",RANDBETWEEN($C$1,$C$2))
... A295: =IFERROR(IF(A294+1>$C$2,"",A294+1),"") | B295: =IF(A295="","",RANDBETWEEN($C$1,$C$2))

Sheet Sheet1
