Workbook

Sheet The IT Life
B2: TOPIC: THE IT LIFE
A3: No | B3: No | C3: ID | D3: Sentence | E3: Type | F3: Link | G3: ID | H3: Copy Google drive to …
B4: 1 | C4: =B4&E4 -> 1Struc | D4: I SET MY CELL PHONE TO… MODE /Tôi chỉnh điện thoại sang chế độ…/ | E4: Struc
A5: 1 | B5: 1.1 | C5: =B5&E5 -> 1.1Viet | D5: Tôi chỉnh điện thoại sang chế độ yên lặng. | E5: Viet | F5: =IF(G5="","","https://docs.google.com/uc?export=download&id="&G5) | G5: =IFERROR(LEFT(RIGHT(H5,LEN(H5)-32),LEN(RIGHT(H5,LEN(H5)-32))-17),"")
B6: 1.1 | C6: =B6&E6 -> 1.1Eng | D6: I set my cell phone to silent mode. | E6: Eng | F6: =IF(G6="","","https://docs.google.com/uc?export=download&id="&G6) -> https://docs.google.com/uc?export=download&id=1eFbkZd-D0AAFL9yfuycArR_LVl3vNnOD | G6: =IFERROR(LEFT(RIGHT(H6,LEN(H6)-32),LEN(RIGHT(H6,LEN(H6)-32))-17),"") -> 1eFbkZd-D0AAFL9yfuycArR_LVl3vNnOD | H6: https://drive.google.com/file/d/1eFbkZd-D0AAFL9yfuycArR_LVl3vNnOD/view?usp=sharing
B7: 1.1 | C7: =B7&E7 -> 1.1Phon | D7: aɪ sɛt maɪ ˈsɛl foʊn tu: ˈsaɪlənt moʊd | E7: Phon | F7: =IF(G7="","","https://docs.google.com/uc?export=download&id="&G7) | G7: =IFERROR(LEFT(RIGHT(H7,LEN(H7)-32),LEN(RIGHT(H7,LEN(H7)-32))-17),"")
A8: 2 | B8: 1.2 | C8: =B8&E8 -> 1.2Viet | D8: Tôi chỉnh điện thoại sang chế độ máy bay. | E8: Viet | F8: =IF(G8="","","https://docs.google.com/uc?export=download&id="&G8) | G8: =IFERROR(LEFT(RIGHT(H8,LEN(H8)-32),LEN(RIGHT(H8,LEN(H8)-32))-17),"")
B9: 1.2 | C9: =B9&E9 -> 1.2Eng | D9: I set my cell phone to airplane mode. | E9: Eng | F9: =IF(G9="","","https://docs.google.com/uc?export=download&id="&G9) -> https://docs.google.com/uc?export=download&id=1ONQ_KclH6zePyZZLCL9qylK9_uP_iWT_ | G9: =IFERROR(LEFT(RIGHT(H9,LEN(H9)-32),LEN(RIGHT(H9,LEN(H9)-32))-17),"") -> 1ONQ_KclH6zePyZZLCL9qylK9_uP_iWT_ | H9: https://drive.google.com/file/d/1ONQ_KclH6zePyZZLCL9qylK9_uP_iWT_/view?usp=sharing
B10: 1.2 | C10: =B10&E10 -> 1.2Phon | D10: aɪ sɛt maɪ ˈsɛl foʊn tu: ˈerpleɪn moʊd | E10: Phon | F10: =IF(G10="","","https://docs.google.com/uc?export=download&id="&G10) | G10: =IFERROR(LEFT(RIGHT(H10,LEN(H10)-32),LEN(RIGHT(H10,LEN(H10)-32))-17),"")
A11: 3 | B11: 1.3 | C11: =B11&E11 -> 1.3Viet | D11: Tôi chỉnh điện thoại sang chế độ ban đêm. | E11: Viet | F11: =IF(G11="","","https://docs.google.com/uc?export=download&id="&G11) | G11: =IFERROR(LEFT(RIGHT(H11,LEN(H11)-32),LEN(RIGHT(H11,LEN(H11)-32))-17),"")
B12: 1.3 | C12: =B12&E12 -> 1.3Eng | D12: I set my cell phone to night mode. | E12: Eng | F12: =IF(G12="","","https://docs.google.com/uc?export=download&id="&G12) -> https://docs.google.com/uc?export=download&id=1W-CY309TE21KEggFTaPrBoCEUoulqc9Y | G12: =IFERROR(LEFT(RIGHT(H12,LEN(H12)-32),LEN(RIGHT(H12,LEN(H12)-32))-17),"") -> 1W-CY309TE21KEggFTaPrBoCEUoulqc9Y | H12: https://drive.google.com/file/d/1W-CY309TE21KEggFTaPrBoCEUoulqc9Y/view?usp=sharing
B13: 1.3 | C13: =B13&E13 -> 1.3Phon | D13: aɪ sɛt maɪ ˈsɛl foʊn tu: naɪt moʊd | E13: Phon | F13: =IF(G13="","","https://docs.google.com/uc?export=download&id="&G13) | G13: =IFERROR(LEFT(RIGHT(H13,LEN(H13)-32),LEN(RIGHT(H13,LEN(H13)-32))-17),"")
A14: 4 | B14: 1.4 | C14: =B14&E14 -> 1.4Viet | D14: Tôi chỉnh điện thoại sang chế độ phòng họp. | E14: Viet | F14: =IF(G14="","","https://docs.google.com/uc?export=download&id="&G14) | G14: =IFERROR(LEFT(RIGHT(H14,LEN(H14)-32),LEN(RIGHT(H14,LEN(H14)-32))-17),"")
B15: 1.4 | C15: =B15&E15 -> 1.4Eng | D15: I set my cell phone to meeting mode. | E15: Eng | F15: =IF(G15="","","https://docs.google.com/uc?export=download&id="&G15) -> https://docs.google.com/uc?export=download&id=1gU3HgG24ZQrA2dxDzYFTEyCy8HBvB1Yt | G15: =IFERROR(LEFT(RIGHT(H15,LEN(H15)-32),LEN(RIGHT(H15,LEN(H15)-32))-17),"") -> 1gU3HgG24ZQrA2dxDzYFTEyCy8HBvB1Yt | H15: https://drive.google.com/file/d/1gU3HgG24ZQrA2dxDzYFTEyCy8HBvB1Yt/view?usp=sharing
B16: 1.4 | C16: =B16&E16 -> 1.4Phon | D16: aɪ sɛt maɪ ˈsɛl foʊn tu: ˈmi:tɪŋ moʊd | E16: Phon | F16: =IF(G16="","","https://docs.google.com/uc?export=download&id="&G16) | G16: =IFERROR(LEFT(RIGHT(H16,LEN(H16)-32),LEN(RIGHT(H16,LEN(H16)-32))-17),"")
B17: 2 | C17: =B17&E17 -> 2Struc | D17: RECHARGE MY + NOUN /Tôi sạc pin…/ | E17: Struc | F17: =IF(G17="","","https://docs.google.com/uc?export=download&id="&G17) | G17: =IFERROR(LEFT(RIGHT(H17,LEN(H17)-32),LEN(RIGHT(H17,LEN(H17)-32))-17),"")
A18: 5 | B18: 2.1 | C18: =B18&E18 -> 2.1Viet | D18: Tôi sạc pin điện thoại của mình. | E18: Viet | F18: =IF(G18="","","https://docs.google.com/uc?export=download&id="&G18) | G18: =IFERROR(LEFT(RIGHT(H18,LEN(H18)-32),LEN(RIGHT(H18,LEN(H18)-32))-17),"")
B19: 2.1 | C19: =B19&E19 -> 2.1Eng | D19: I recharge my cell phone. | E19: Eng | F19: =IF(G19="","","https://docs.google.com/uc?export=download&id="&G19) -> https://docs.google.com/uc?export=download&id=1Ro3044QFltt7T7cUvNlwYs8H-FwT60Yi | G19: =IFERROR(LEFT(RIGHT(H19,LEN(H19)-32),LEN(RIGHT(H19,LEN(H19)-32))-17),"") -> 1Ro3044QFltt7T7cUvNlwYs8H-FwT60Yi | H19: https://drive.google.com/file/d/1Ro3044QFltt7T7cUvNlwYs8H-FwT60Yi/view?usp=sharing
B20: 2.1 | C20: =B20&E20 -> 2.1Phon | D20: aɪ ri:ˈʧa:rʤ maɪ ˈsɛl foʊn | E20: Phon | F20: =IF(G20="","","https://docs.google.com/uc?export=download&id="&G20) | G20: =IFERROR(LEFT(RIGHT(H20,LEN(H20)-32),LEN(RIGHT(H20,LEN(H20)-32))-17),"")
A21: 6 | B21: 2.2 | C21: =B21&E21 -> 2.2Viet | D21: Tôi sạc điện thoại ở đây được không? | E21: Viet | F21: =IF(G21="","","https://docs.google.com/uc?export=download&id="&G21) | G21: =IFERROR(LEFT(RIGHT(H21,LEN(H21)-32),LEN(RIGHT(H21,LEN(H21)-32))-17),"")
B22: 2.2 | C22: =B22&E22 -> 2.2Eng | D22: Can I recharge my cell phone here? | E22: Eng | F22: =IF(G22="","","https://docs.google.com/uc?export=download&id="&G22) -> https://docs.google.com/uc?export=download&id=1GA4tAINFysygMz24fePZvMpIA4UfhRld | G22: =IFERROR(LEFT(RIGHT(H22,LEN(H22)-32),LEN(RIGHT(H22,LEN(H22)-32))-17),"") -> 1GA4tAINFysygMz24fePZvMpIA4UfhRld | H22: https://drive.google.com/file/d/1GA4tAINFysygMz24fePZvMpIA4UfhRld/view?usp=sharing
B23: 2.2 | C23: =B23&E23 -> 2.2Phon | D23: kæn aɪ ri:ˈʧa:rʤ maɪ ˈsɛl foʊn hɪr | E23: Phon | F23: =IF(G23="","","https://docs.google.com/uc?export=download&id="&G23) | G23: =IFERROR(LEFT(RIGHT(H23,LEN(H23)-32),LEN(RIGHT(H23,LEN(H23)-32))-17),"")
A24: 7 | B24: 2.3 | C24: =B24&E24 -> 2.3Viet | D24: Tôi sạc pin điện thoại của mình 2 lần 1 ngày. | E24: Viet | F24: =IF(G24="","","https://docs.google.com/uc?export=download&id="&G24) | G24: =IFERROR(LEFT(RIGHT(H24,LEN(H24)-32),LEN(RIGHT(H24,LEN(H24)-32))-17),"")
B25: 2.3 | C25: =B25&E25 -> 2.3Eng | D25: I recharge my cell phone twice a day. | E25: Eng | F25: =IF(G25="","","https://docs.google.com/uc?export=download&id="&G25) -> https://docs.google.com/uc?export=download&id=1Eq1APWBpLLpeZjB0xACYOgOVC54W8_qG | G25: =IFERROR(LEFT(RIGHT(H25,LEN(H25)-32),LEN(RIGHT(H25,LEN(H25)-32))-17),"") -> 1Eq1APWBpLLpeZjB0xACYOgOVC54W8_qG | H25: https://drive.google.com/file/d/1Eq1APWBpLLpeZjB0xACYOgOVC54W8_qG/view?usp=sharing
B26: 2.3 | C26: =B26&E26 -> 2.3Phon | D26: aɪ ri:ˈʧa:rʤ maɪ ˈsɛl foʊn twaɪs ə deɪ | E26: Phon | F26: =IF(G26="","","https://docs.google.com/uc?export=download&id="&G26) | G26: =IFERROR(LEFT(RIGHT(H26,LEN(H26)-32),LEN(RIGHT(H26,LEN(H26)-32))-17),"")
B27: 3 | C27: =B27&E27 -> 3Struc | D27: I CONNECT SOMETHING TO SOMETHING /Tôi kết nối cái gì với cái gì…/ | E27: Struc | F27: =IF(G27="","","https://docs.google.com/uc?export=download&id="&G27) | G27: =IFERROR(LEFT(RIGHT(H27,LEN(H27)-32),LEN(RIGHT(H27,LEN(H27)-32))-17),"")
A28: 8 | B28: 3.1 | C28: =B28&E28 -> 3.1Viet | D28: Tôi kết nối máy in với máy tính. | E28: Viet | F28: =IF(G28="","","https://docs.google.com/uc?export=download&id="&G28) | G28: =IFERROR(LEFT(RIGHT(H28,LEN(H28)-32),LEN(RIGHT(H28,LEN(H28)-32))-17),"")
B29: 3.1 | C29: =B29&E29 -> 3.1Eng | D29: I connect the printer to the computer. | E29: Eng | F29: =IF(G29="","","https://docs.google.com/uc?export=download&id="&G29) -> https://docs.google.com/uc?export=download&id=1MCRBhoGBxeC6y8du1IVW1L8LAeRr3jqq | G29: =IFERROR(LEFT(RIGHT(H29,LEN(H29)-32),LEN(RIGHT(H29,LEN(H29)-32))-17),"") -> 1MCRBhoGBxeC6y8du1IVW1L8LAeRr3jqq | H29: https://drive.google.com/file/d/1MCRBhoGBxeC6y8du1IVW1L8LAeRr3jqq/view?usp=sharing
B30: 3.1 | C30: =B30&E30 -> 3.1Phon | D30: aɪ kəˈnɛkt ðə ˈprɪntər tu: ðə kəmˈpju:tər | E30: Phon | F30: =IF(G30="","","https://docs.google.com/uc?export=download&id="&G30) | G30: =IFERROR(LEFT(RIGHT(H30,LEN(H30)-32),LEN(RIGHT(H30,LEN(H30)-32))-17),"")
A31: 9 | B31: 3.2 | C31: =B31&E31 -> 3.2Viet | D31: Tôi kết nối điện thoại với cái loa bluetooth. | E31: Viet | F31: =IF(G31="","","https://docs.google.com/uc?export=download&id="&G31) | G31: =IFERROR(LEFT(RIGHT(H31,LEN(H31)-32),LEN(RIGHT(H31,LEN(H31)-32))-17),"")
B32: 3.2 | C32: =B32&E32 -> 3.2Eng | D32: I connect my smartphone to the bluetooth speaker. | E32: Eng | F32: =IF(G32="","","https://docs.google.com/uc?export=download&id="&G32) -> https://docs.google.com/uc?export=download&id=13DOWP5CcepnrfI3uvW1PF6bxiOUVpAHM | G32: =IFERROR(LEFT(RIGHT(H32,LEN(H32)-32),LEN(RIGHT(H32,LEN(H32)-32))-17),"") -> 13DOWP5CcepnrfI3uvW1PF6bxiOUVpAHM | H32: https://drive.google.com/file/d/13DOWP5CcepnrfI3uvW1PF6bxiOUVpAHM/view?usp=sharing
B33: 3.2 | C33: =B33&E33 -> 3.2Phon | D33: aɪ kəˈnɛkt maɪ ˈsma:rtfoʊn tu: ðə ˈblu:tu:θ ˈspi:kər | E33: Phon | F33: =IF(G33="","","https://docs.google.com/uc?export=download&id="&G33) | G33: =IFERROR(LEFT(RIGHT(H33,LEN(H33)-32),LEN(RIGHT(H33,LEN(H33)-32))-17),"")
A34: 10 | B34: 3.3 | C34: =B34&E34 -> 3.3Viet | D34: Tôi kết nối điện thoại với máy tính. | E34: Viet | F34: =IF(G34="","","https://docs.google.com/uc?export=download&id="&G34) | G34: =IFERROR(LEFT(RIGHT(H34,LEN(H34)-32),LEN(RIGHT(H34,LEN(H34)-32))-17),"")
B35: 3.3 | C35: =B35&E35 -> 3.3Eng | D35: I connect my smartphone to the computer. | E35: Eng | F35: =IF(G35="","","https://docs.google.com/uc?export=download&id="&G35) -> https://docs.google.com/uc?export=download&id=1KNW93gQ9isYuoe9vZCRmoPdL4BwHOASn | G35: =IFERROR(LEFT(RIGHT(H35,LEN(H35)-32),LEN(RIGHT(H35,LEN(H35)-32))-17),"") -> 1KNW93gQ9isYuoe9vZCRmoPdL4BwHOASn | H35: https://drive.google.com/file/d/1KNW93gQ9isYuoe9vZCRmoPdL4BwHOASn/view?usp=sharing
B36: 3.3 | C36: =B36&E36 -> 3.3Phon | D36: aɪ kəˈnɛkt maɪ ˈsma:rtfoʊn tu: ðə kəmˈpju:tər | E36: Phon | F36: =IF(G36="","","https://docs.google.com/uc?export=download&id="&G36) | G36: =IFERROR(LEFT(RIGHT(H36,LEN(H36)-32),LEN(RIGHT(H36,LEN(H36)-32))-17),"")
A37: 11 | B37: 3.4 | C37: =B37&E37 -> 3.4Viet | D37: Tôi kết nối điện thoại với wifi. | E37: Viet | F37: =IF(G37="","","https://docs.google.com/uc?export=download&id="&G37) | G37: =IFERROR(LEFT(RIGHT(H37,LEN(H37)-32),LEN(RIGHT(H37,LEN(H37)-32))-17),"")
B38: 3.4 | C38: =B38&E38 -> 3.4Eng | D38: I connect my smartphone to wifi. | E38: Eng | F38: =IF(G38="","","https://docs.google.com/uc?export=download&id="&G38) -> https://docs.google.com/uc?export=download&id=1tqg_Hk61k0MGfGaRqTjTWrQUBAzVem9r | G38: =IFERROR(LEFT(RIGHT(H38,LEN(H38)-32),LEN(RIGHT(H38,LEN(H38)-32))-17),"") -> 1tqg_Hk61k0MGfGaRqTjTWrQUBAzVem9r | H38: https://drive.google.com/file/d/1tqg_Hk61k0MGfGaRqTjTWrQUBAzVem9r/view?usp=sharing
B39: 3.4 | C39: =B39&E39 -> 3.4Phon | D39: aɪ kəˈnɛkt maɪ ˈsma:rtfoʊn tu: ˈwaɪfaɪ | E39: Phon | F39: =IF(G39="","","https://docs.google.com/uc?export=download&id="&G39) | G39: =IFERROR(LEFT(RIGHT(H39,LEN(H39)-32),LEN(RIGHT(H39,LEN(H39)-32))-17),"")
B40: 4 | C40: =B40&E40 -> 4Struc | D40: I + VERB + NOUN AND SEND IT /Tôi làm một cái gì đó rồi gửi đi/ | E40: Struc | F40: =IF(G40="","","https://docs.google.com/uc?export=download&id="&G40) | G40: =IFERROR(LEFT(RIGHT(H40,LEN(H40)-32),LEN(RIGHT(H40,LEN(H40)-32))-17),"")
A41: 12 | B41: 4.1 | C41: =B41&E41 -> 4.1Viet | D41: Tôi chụp hình bằng camera điện thoại rồi gửi đi. | E41: Viet | F41: =IF(G41="","","https://docs.google.com/uc?export=download&id="&G41) | G41: =IFERROR(LEFT(RIGHT(H41,LEN(H41)-32),LEN(RIGHT(H41,LEN(H41)-32))-17),"")
B42: 4.1 | C42: =B42&E42 -> 4.1Eng | D42: I take a photo with my cell phone camera and send it. | E42: Eng | F42: =IF(G42="","","https://docs.google.com/uc?export=download&id="&G42) -> https://docs.google.com/uc?export=download&id=1dQOJ-AnZee4X0oE_QkOfvf0vI2r-dZyD | G42: =IFERROR(LEFT(RIGHT(H42,LEN(H42)-32),LEN(RIGHT(H42,LEN(H42)-32))-17),"") -> 1dQOJ-AnZee4X0oE_QkOfvf0vI2r-dZyD | H42: https://drive.google.com/file/d/1dQOJ-AnZee4X0oE_QkOfvf0vI2r-dZyD/view?usp=sharing
B43: 4.1 | C43: =B43&E43 -> 4.1Phon | D43: aɪ teɪk ə ˈfoʊtoʊ wɪð maɪ ˈsɛl foʊn ˈkæmrə ænd sɛnd ɪt | E43: Phon | F43: =IF(G43="","","https://docs.google.com/uc?export=download&id="&G43) | G43: =IFERROR(LEFT(RIGHT(H43,LEN(H43)-32),LEN(RIGHT(H43,LEN(H43)-32))-17),"")
A44: 13 | B44: 4.2 | C44: =B44&E44 -> 4.2Viet | D44: Tôi quay phim bằng camera điện thoại rồi gửi đi. | E44: Viet | F44: =IF(G44="","","https://docs.google.com/uc?export=download&id="&G44) | G44: =IFERROR(LEFT(RIGHT(H44,LEN(H44)-32),LEN(RIGHT(H44,LEN(H44)-32))-17),"")
B45: 4.2 | C45: =B45&E45 -> 4.2Eng | D45: I record a video with my cell phone and send it. | E45: Eng | F45: =IF(G45="","","https://docs.google.com/uc?export=download&id="&G45) -> https://docs.google.com/uc?export=download&id=1vXsgNfTykocf_78BAO9BM32t_cyf_EVR | G45: =IFERROR(LEFT(RIGHT(H45,LEN(H45)-32),LEN(RIGHT(H45,LEN(H45)-32))-17),"") -> 1vXsgNfTykocf_78BAO9BM32t_cyf_EVR | H45: https://drive.google.com/file/d/1vXsgNfTykocf_78BAO9BM32t_cyf_EVR/view?usp=sharing
B46: 4.2 | C46: =B46&E46 -> 4.2Phon | D46: aɪ rɪˈkɔ:rd ə ˈvɪdioʊ wɪð maɪ ˈsɛl foʊn ænd sɛnd ɪt | E46: Phon | F46: =IF(G46="","","https://docs.google.com/uc?export=download&id="&G46) | G46: =IFERROR(LEFT(RIGHT(H46,LEN(H46)-32),LEN(RIGHT(H46,LEN(H46)-32))-17),"")
A47: 14 | B47: 4.3 | C47: =B47&E47 -> 4.3Viet | D47: Tôi đánh một tin nhắn bằng điện thoại rồi gửi đi. | E47: Viet | F47: =IF(G47="","","https://docs.google.com/uc?export=download&id="&G47) | G47: =IFERROR(LEFT(RIGHT(H47,LEN(H47)-32),LEN(RIGHT(H47,LEN(H47)-32))-17),"")
B48: 4.3 | C48: =B48&E48 -> 4.3Eng | D48: I text a message with my cell phone and send it. | E48: Eng | F48: =IF(G48="","","https://docs.google.com/uc?export=download&id="&G48) -> https://docs.google.com/uc?export=download&id=1jRLag9BaFG3AvNWkAZ4UmMPBYa9Uk5Ie | G48: =IFERROR(LEFT(RIGHT(H48,LEN(H48)-32),LEN(RIGHT(H48,LEN(H48)-32))-17),"") -> 1jRLag9BaFG3AvNWkAZ4UmMPBYa9Uk5Ie | H48: https://drive.google.com/file/d/1jRLag9BaFG3AvNWkAZ4UmMPBYa9Uk5Ie/view?usp=sharing
B49: 4.3 | C49: =B49&E49 -> 4.3Phon | D49: aɪ tɛkst ə ˈmɛsɪʤ wɪð maɪ ˈsɛl foʊn ænd sɛnd ɪt | E49: Phon | F49: =IF(G49="","","https://docs.google.com/uc?export=download&id="&G49) | G49: =IFERROR(LEFT(RIGHT(H49,LEN(H49)-32),LEN(RIGHT(H49,LEN(H49)-32))-17),"")
A50: 15 | B50: 4.4 | C50: =B50&E50 -> 4.4Viet | D50: Tôi thu âm bằng điện thoại rồi gửi đi. | E50: Viet | F50: =IF(G50="","","https://docs.google.com/uc?export=download&id="&G50) | G50: =IFERROR(LEFT(RIGHT(H50,LEN(H50)-32),LEN(RIGHT(H50,LEN(H50)-32))-17),"")
B51: 4.4 | C51: =B51&E51 -> 4.4Eng | D51: I record with my cell phone and send it. | E51: Eng | F51: =IF(G51="","","https://docs.google.com/uc?export=download&id="&G51) -> https://docs.google.com/uc?export=download&id=128VtKzNXRUog8g5_3fBk9WwXSjZoYb-e | G51: =IFERROR(LEFT(RIGHT(H51,LEN(H51)-32),LEN(RIGHT(H51,LEN(H51)-32))-17),"") -> 128VtKzNXRUog8g5_3fBk9WwXSjZoYb-e | H51: https://drive.google.com/file/d/128VtKzNXRUog8g5_3fBk9WwXSjZoYb-e/view?usp=sharing
B52: 4.4 | C52: =B52&E52 -> 4.4Phon | D52: aɪ rɪˈkɔ:rd wɪð maɪ ˈsɛl foʊn ænd sɛnd ɪt | E52: Phon | F52: =IF(G52="","","https://docs.google.com/uc?export=download&id="&G52) | G52: =IFERROR(LEFT(RIGHT(H52,LEN(H52)-32),LEN(RIGHT(H52,LEN(H52)-32))-17),"")
B53: 5 | C53: =B53&E53 -> 5Struc | D53: I RESPOND TO + NOUN /Tôi trả lời…/ | E53: Struc | F53: =IF(G53="","","https://docs.google.com/uc?export=download&id="&G53) | G53: =IFERROR(LEFT(RIGHT(H53,LEN(H53)-32),LEN(RIGHT(H53,LEN(H53)-32))-17),"")
A54: 16 | B54: 5.1 | C54: =B54&E54 -> 5.1Viet | D54: Tôi trả lời một tin nhắn. | E54: Viet | F54: =IF(G54="","","https://docs.google.com/uc?export=download&id="&G54) | G54: =IFERROR(LEFT(RIGHT(H54,LEN(H54)-32),LEN(RIGHT(H54,LEN(H54)-32))-17),"")
B55: 5.1 | C55: =B55&E55 -> 5.1Eng | D55: I respond to a message. | E55: Eng | F55: =IF(G55="","","https://docs.google.com/uc?export=download&id="&G55) -> https://docs.google.com/uc?export=download&id=1hvT1H2FqXwXb1wzPAJwUw9Oj9IVxnbTP | G55: =IFERROR(LEFT(RIGHT(H55,LEN(H55)-32),LEN(RIGHT(H55,LEN(H55)-32))-17),"") -> 1hvT1H2FqXwXb1wzPAJwUw9Oj9IVxnbTP | H55: https://drive.google.com/file/d/1hvT1H2FqXwXb1wzPAJwUw9Oj9IVxnbTP/view?usp=sharing
B56: 5.1 | C56: =B56&E56 -> 5.1Phon | D56: aɪ rɪˈspa:nd tu: ə ˈmɛsɪʤ | E56: Phon | F56: =IF(G56="","","https://docs.google.com/uc?export=download&id="&G56) | G56: =IFERROR(LEFT(RIGHT(H56,LEN(H56)-32),LEN(RIGHT(H56,LEN(H56)-32))-17),"")
A57: 17 | B57: 5.2 | C57: =B57&E57 -> 5.2Viet | D57: Tôi trả lời một email. | E57: Viet | F57: =IF(G57="","","https://docs.google.com/uc?export=download&id="&G57) | G57: =IFERROR(LEFT(RIGHT(H57,LEN(H57)-32),LEN(RIGHT(H57,LEN(H57)-32))-17),"")
B58: 5.2 | C58: =B58&E58 -> 5.2Eng | D58: I respond to an email. | E58: Eng | F58: =IF(G58="","","https://docs.google.com/uc?export=download&id="&G58) -> https://docs.google.com/uc?export=download&id=1ZRb7LZHkMBZgedtAgWQPfOey_D4u8ofU | G58: =IFERROR(LEFT(RIGHT(H58,LEN(H58)-32),LEN(RIGHT(H58,LEN(H58)-32))-17),"") -> 1ZRb7LZHkMBZgedtAgWQPfOey_D4u8ofU | H58: https://drive.google.com/file/d/1ZRb7LZHkMBZgedtAgWQPfOey_D4u8ofU/view?usp=sharing
B59: 5.2 | C59: =B59&E59 -> 5.2Phon | D59: aɪ rɪˈspa:nd tu: ən ˈi:meɪl | E59: Phon | F59: =IF(G59="","","https://docs.google.com/uc?export=download&id="&G59) | G59: =IFERROR(LEFT(RIGHT(H59,LEN(H59)-32),LEN(RIGHT(H59,LEN(H59)-32))-17),"")
A60: 18 | B60: 5.3 | C60: =B60&E60 -> 5.3Viet | D60: Tôi trả lời một bình luận. | E60: Viet | F60: =IF(G60="","","https://docs.google.com/uc?export=download&id="&G60) | G60: =IFERROR(LEFT(RIGHT(H60,LEN(H60)-32),LEN(RIGHT(H60,LEN(H60)-32))-17),"")
B61: 5.3 | C61: =B61&E61 -> 5.3Eng | D61: I respond to a comment. | E61: Eng | F61: =IF(G61="","","https://docs.google.com/uc?export=download&id="&G61) -> https://docs.google.com/uc?export=download&id=1PJD1SR_BgH94MZM4VngvRFXdSX44PsUN | G61: =IFERROR(LEFT(RIGHT(H61,LEN(H61)-32),LEN(RIGHT(H61,LEN(H61)-32))-17),"") -> 1PJD1SR_BgH94MZM4VngvRFXdSX44PsUN | H61: https://drive.google.com/file/d/1PJD1SR_BgH94MZM4VngvRFXdSX44PsUN/view?usp=sharing
B62: 5.3 | C62: =B62&E62 -> 5.3Phon | D62: aɪ rɪˈspa:nd tu: ə ˈka:mɛnt | E62: Phon | F62: =IF(G62="","","https://docs.google.com/uc?export=download&id="&G62) | G62: =IFERROR(LEFT(RIGHT(H62,LEN(H62)-32),LEN(RIGHT(H62,LEN(H62)-32))-17),"")
B63: 6 | C63: =B63&E63 -> 6Struc | D63: I PUT A LINK IN MY + NOUN /Tôi đặt một đường link trong…/ | E63: Struc | F63: =IF(G63="","","https://docs.google.com/uc?export=download&id="&G63) | G63: =IFERROR(LEFT(RIGHT(H63,LEN(H63)-32),LEN(RIGHT(H63,LEN(H63)-32))-17),"")
A64: 19 | B64: 6.1 | C64: =B64&E64 -> 6.1Viet | D64: Tôi đặt một đường link trong bài đăng của mình. | E64: Viet | F64: =IF(G64="","","https://docs.google.com/uc?export=download&id="&G64) | G64: =IFERROR(LEFT(RIGHT(H64,LEN(H64)-32),LEN(RIGHT(H64,LEN(H64)-32))-17),"")
B65: 6.1 | C65: =B65&E65 -> 6.1Eng | D65: I put a link in my post. | E65: Eng | F65: =IF(G65="","","https://docs.google.com/uc?export=download&id="&G65) -> https://docs.google.com/uc?export=download&id=1hBU6ciyl59HlcpZKvrCXnPj2WK0xHVTc | G65: =IFERROR(LEFT(RIGHT(H65,LEN(H65)-32),LEN(RIGHT(H65,LEN(H65)-32))-17),"") -> 1hBU6ciyl59HlcpZKvrCXnPj2WK0xHVTc | H65: https://drive.google.com/file/d/1hBU6ciyl59HlcpZKvrCXnPj2WK0xHVTc/view?usp=sharing
B66: 6.1 | C66: =B66&E66 -> 6.1Phon | D66: aɪ pʊt ə lɪŋk ɪn maɪ poʊst | E66: Phon | F66: =IF(G66="","","https://docs.google.com/uc?export=download&id="&G66) | G66: =IFERROR(LEFT(RIGHT(H66,LEN(H66)-32),LEN(RIGHT(H66,LEN(H66)-32))-17),"")
A67: 20 | B67: 6.2 | C67: =B67&E67 -> 6.2Viet | D67: Tôi đặt một đường link trong hình ảnh của mình. | E67: Viet | F67: =IF(G67="","","https://docs.google.com/uc?export=download&id="&G67) | G67: =IFERROR(LEFT(RIGHT(H67,LEN(H67)-32),LEN(RIGHT(H67,LEN(H67)-32))-17),"")
B68: 6.2 | C68: =B68&E68 -> 6.2Eng | D68: I put a link in my image. | E68: Eng | F68: =IF(G68="","","https://docs.google.com/uc?export=download&id="&G68) -> https://docs.google.com/uc?export=download&id=1LmVRZfRES4K8_DTFLzBFh5op_CZeb-cb | G68: =IFERROR(LEFT(RIGHT(H68,LEN(H68)-32),LEN(RIGHT(H68,LEN(H68)-32))-17),"") -> 1LmVRZfRES4K8_DTFLzBFh5op_CZeb-cb | H68: https://drive.google.com/file/d/1LmVRZfRES4K8_DTFLzBFh5op_CZeb-cb/view?usp=sharing
B69: 6.2 | C69: =B69&E69 -> 6.2Phon | D69: aɪ pʊt ə lɪŋk ɪn maɪ ˈɪmɪʤ | E69: Phon | F69: =IF(G69="","","https://docs.google.com/uc?export=download&id="&G69) | G69: =IFERROR(LEFT(RIGHT(H69,LEN(H69)-32),LEN(RIGHT(H69,LEN(H69)-32))-17),"")
A70: 21 | B70: 6.3 | C70: =B70&E70 -> 6.3Viet | D70: Tôi đặt một đường link trong email của mình. | E70: Viet | F70: =IF(G70="","","https://docs.google.com/uc?export=download&id="&G70) | G70: =IFERROR(LEFT(RIGHT(H70,LEN(H70)-32),LEN(RIGHT(H70,LEN(H70)-32))-17),"")
B71: 6.3 | C71: =B71&E71 -> 6.3Eng | D71: I put a link in my email. | E71: Eng | F71: =IF(G71="","","https://docs.google.com/uc?export=download&id="&G71) -> https://docs.google.com/uc?export=download&id=1Ee9B1r47UDLpesTPjLeTjDv8RRfdenvV | G71: =IFERROR(LEFT(RIGHT(H71,LEN(H71)-32),LEN(RIGHT(H71,LEN(H71)-32))-17),"") -> 1Ee9B1r47UDLpesTPjLeTjDv8RRfdenvV | H71: https://drive.google.com/file/d/1Ee9B1r47UDLpesTPjLeTjDv8RRfdenvV/view?usp=sharing
B72: 6.3 | C72: =B72&E72 -> 6.3Phon | D72: aɪ pʊt ə lɪŋk ɪn maɪ ˈi:meɪl | E72: Phon | F72: =IF(G72="","","https://docs.google.com/uc?export=download&id="&G72) | G72: =IFERROR(LEFT(RIGHT(H72,LEN(H72)-32),LEN(RIGHT(H72,LEN(H72)-32))-17),"")
A73: 22 | B73: 6.4 | C73: =B73&E73 -> 6.4Viet | D73: Tôi đặt một đường link trong phần mô tả của mình. | E73: Viet | F73: =IF(G73="","","https://docs.google.com/uc?export=download&id="&G73) | G73: =IFERROR(LEFT(RIGHT(H73,LEN(H73)-32),LEN(RIGHT(H73,LEN(H73)-32))-17),"")
B74: 6.4 | C74: =B74&E74 -> 6.4Eng | D74: I put a link in my description. | E74: Eng | F74: =IF(G74="","","https://docs.google.com/uc?export=download&id="&G74) -> https://docs.google.com/uc?export=download&id=1IjEv3OJctfO4nC0tDSDoEnbRqBFy-Ifl | G74: =IFERROR(LEFT(RIGHT(H74,LEN(H74)-32),LEN(RIGHT(H74,LEN(H74)-32))-17),"") -> 1IjEv3OJctfO4nC0tDSDoEnbRqBFy-Ifl | H74: https://drive.google.com/file/d/1IjEv3OJctfO4nC0tDSDoEnbRqBFy-Ifl/view?usp=sharing
B75: 6.4 | C75: =B75&E75 -> 6.4Phon | D75: aɪ pʊt ə lɪŋk ɪn maɪ dɪˈskrɪpʃən | E75: Phon | F75: =IF(G75="","","https://docs.google.com/uc?export=download&id="&G75) | G75: =IFERROR(LEFT(RIGHT(H75,LEN(H75)-32),LEN(RIGHT(H75,LEN(H75)-32))-17),"")
B76: 7 | C76: =B76&E76 -> 7Struc | D76: I USE MY PHONE TO + VERB /Tôi dùng điện thoại để…/ | E76: Struc | F76: =IF(G76="","","https://docs.google.com/uc?export=download&id="&G76) | G76: =IFERROR(LEFT(RIGHT(H76,LEN(H76)-32),LEN(RIGHT(H76,LEN(H76)-32))-17),"")
A77: 23 | B77: 7.1 | C77: =B77&E77 -> 7.1Viet | D77: Tôi dùng điện thoại để gọi điện. | E77: Viet | F77: =IF(G77="","","https://docs.google.com/uc?export=download&id="&G77) | G77: =IFERROR(LEFT(RIGHT(H77,LEN(H77)-32),LEN(RIGHT(H77,LEN(H77)-32))-17),"")
B78: 7.1 | C78: =B78&E78 -> 7.1Eng | D78: I use my phone to make a phone call. | E78: Eng | F78: =IF(G78="","","https://docs.google.com/uc?export=download&id="&G78) -> https://docs.google.com/uc?export=download&id=1KvOcNqSN12WFPqLz6RsXyitKPygenqUc | G78: =IFERROR(LEFT(RIGHT(H78,LEN(H78)-32),LEN(RIGHT(H78,LEN(H78)-32))-17),"") -> 1KvOcNqSN12WFPqLz6RsXyitKPygenqUc | H78: https://drive.google.com/file/d/1KvOcNqSN12WFPqLz6RsXyitKPygenqUc/view?usp=sharing
B79: 7.1 | C79: =B79&E79 -> 7.1Phon | D79: aɪ ju:z maɪ foʊn tu meɪk ə foʊn ka:l | E79: Phon | F79: =IF(G79="","","https://docs.google.com/uc?export=download&id="&G79) | G79: =IFERROR(LEFT(RIGHT(H79,LEN(H79)-32),LEN(RIGHT(H79,LEN(H79)-32))-17),"")
A80: 24 | B80: 7.2 | C80: =B80&E80 -> 7.2Viet | D80: Tôi dùng điện thoại để chụp hình. | E80: Viet | F80: =IF(G80="","","https://docs.google.com/uc?export=download&id="&G80) | G80: =IFERROR(LEFT(RIGHT(H80,LEN(H80)-32),LEN(RIGHT(H80,LEN(H80)-32))-17),"")
B81: 7.2 | C81: =B81&E81 -> 7.2Eng | D81: I use my phone to take photos. | E81: Eng | F81: =IF(G81="","","https://docs.google.com/uc?export=download&id="&G81) -> https://docs.google.com/uc?export=download&id=1slldgTFp2ggILvyNsX4McJ5POOI4sJRj | G81: =IFERROR(LEFT(RIGHT(H81,LEN(H81)-32),LEN(RIGHT(H81,LEN(H81)-32))-17),"") -> 1slldgTFp2ggILvyNsX4McJ5POOI4sJRj | H81: https://drive.google.com/file/d/1slldgTFp2ggILvyNsX4McJ5POOI4sJRj/view?usp=sharing
B82: 7.2 | C82: =B82&E82 -> 7.2Phon | D82: aɪ ju:z maɪ foʊn tu: teɪk ˈfoʊtoʊz | E82: Phon | F82: =IF(G82="","","https://docs.google.com/uc?export=download&id="&G82) | G82: =IFERROR(LEFT(RIGHT(H82,LEN(H82)-32),LEN(RIGHT(H82,LEN(H82)-32))-17),"")
A83: 25 | B83: 7.3 | C83: =B83&E83 -> 7.3Viet | D83: Tôi dùng điện thoại để kết nối internet. | E83: Viet | F83: =IF(G83="","","https://docs.google.com/uc?export=download&id="&G83) | G83: =IFERROR(LEFT(RIGHT(H83,LEN(H83)-32),LEN(RIGHT(H83,LEN(H83)-32))-17),"")
B84: 7.3 | C84: =B84&E84 -> 7.3Eng | D84: I use my phone to access the internet. | E84: Eng | F84: =IF(G84="","","https://docs.google.com/uc?export=download&id="&G84) -> https://docs.google.com/uc?export=download&id=1qUu7o3iJxIAL6RDQeZ0wXPwdKmD7EM2x | G84: =IFERROR(LEFT(RIGHT(H84,LEN(H84)-32),LEN(RIGHT(H84,LEN(H84)-32))-17),"") -> 1qUu7o3iJxIAL6RDQeZ0wXPwdKmD7EM2x | H84: https://drive.google.com/file/d/1qUu7o3iJxIAL6RDQeZ0wXPwdKmD7EM2x/view?usp=sharing
B85: 7.3 | C85: =B85&E85 -> 7.3Phon | D85: aɪ ju:z maɪ foʊn tu ˈæksɛs ði: ˈɪntərnɛt | E85: Phon | F85: =IF(G85="","","https://docs.google.com/uc?export=download&id="&G85) | G85: =IFERROR(LEFT(RIGHT(H85,LEN(H85)-32),LEN(RIGHT(H85,LEN(H85)-32))-17),"")
A86: 26 | B86: 7.4 | C86: =B86&E86 -> 7.4Viet | D86: Tôi dùng điện thoại để gửi tin nhắn. | E86: Viet | F86: =IF(G86="","","https://docs.google.com/uc?export=download&id="&G86) | G86: =IFERROR(LEFT(RIGHT(H86,LEN(H86)-32),LEN(RIGHT(H86,LEN(H86)-32))-17),"")
B87: 7.4 | C87: =B87&E87 -> 7.4Eng | D87: I use my phone to send messages. | E87: Eng | F87: =IF(G87="","","https://docs.google.com/uc?export=download&id="&G87) -> https://docs.google.com/uc?export=download&id=1j9RuEm0_mKdemHAJnwsYfDkicY8AFCW5 | G87: =IFERROR(LEFT(RIGHT(H87,LEN(H87)-32),LEN(RIGHT(H87,LEN(H87)-32))-17),"") -> 1j9RuEm0_mKdemHAJnwsYfDkicY8AFCW5 | H87: https://drive.google.com/file/d/1j9RuEm0_mKdemHAJnwsYfDkicY8AFCW5/view?usp=sharing
B88: 7.4 | C88: =B88&E88 -> 7.4Phon | D88: aɪ ju:z maɪ foʊn tu sɛnd ˈmɛsəʤəz | E88: Phon | F88: =IF(G88="","","https://docs.google.com/uc?export=download&id="&G88) | G88: =IFERROR(LEFT(RIGHT(H88,LEN(H88)-32),LEN(RIGHT(H88,LEN(H88)-32))-17),"")
B89: 8 | C89: =B89&E89 -> 8Struc | D89: MY CELL PHONE IS OUT OF SERVICE NOW BECAUSE… /Điện thoại của tôi đang nằm ngoài vùng phủ sóng do…/ | E89: Struc | F89: =IF(G89="","","https://docs.google.com/uc?export=download&id="&G89) | G89: =IFERROR(LEFT(RIGHT(H89,LEN(H89)-32),LEN(RIGHT(H89,LEN(H89)-32))-17),"")
A90: 27 | B90: 8.1 | C90: =B90&E90 -> 8.1Viet | D90: Điện thoại của tôi đang nằm ngoài vùng phủ sóng do tôi đang ở trong tầng hầm. | E90: Viet | F90: =IF(G90="","","https://docs.google.com/uc?export=download&id="&G90) | G90: =IFERROR(LEFT(RIGHT(H90,LEN(H90)-32),LEN(RIGHT(H90,LEN(H90)-32))-17),"")
B91: 8.1 | C91: =B91&E91 -> 8.1Eng | D91: My cell phone is out of service now because I’m in the basement. | E91: Eng | F91: =IF(G91="","","https://docs.google.com/uc?export=download&id="&G91) -> https://docs.google.com/uc?export=download&id=1mq7iYs_Z1bRAEpHietFCW0kT_BsxFcd8 | G91: =IFERROR(LEFT(RIGHT(H91,LEN(H91)-32),LEN(RIGHT(H91,LEN(H91)-32))-17),"") -> 1mq7iYs_Z1bRAEpHietFCW0kT_BsxFcd8 | H91: https://drive.google.com/file/d/1mq7iYs_Z1bRAEpHietFCW0kT_BsxFcd8/view?usp=sharing
B92: 8.1 | C92: =B92&E92 -> 8.1Phon | D92: maɪ ˈsɛl foʊn ɪz aʊt ʌv ˈsɜ:rvɪs naʊ bɪˈkəz aɪm ɪn ðə ˈbeɪsmənt | E92: Phon | F92: =IF(G92="","","https://docs.google.com/uc?export=download&id="&G92) | G92: =IFERROR(LEFT(RIGHT(H92,LEN(H92)-32),LEN(RIGHT(H92,LEN(H92)-32))-17),"")
A93: 28 | B93: 8.2 | C93: =B93&E93 -> 8.2Viet | D93: Điện thoại của tôi đang nằm ngoài vùng phủ sóng do tôi đang bật chế độ máy bay. | E93: Viet | F93: =IF(G93="","","https://docs.google.com/uc?export=download&id="&G93) | G93: =IFERROR(LEFT(RIGHT(H93,LEN(H93)-32),LEN(RIGHT(H93,LEN(H93)-32))-17),"")
B94: 8.2 | C94: =B94&E94 -> 8.2Eng | D94: My cell phone is out of service now because I turn on the airplane mode. | E94: Eng | F94: =IF(G94="","","https://docs.google.com/uc?export=download&id="&G94) -> https://docs.google.com/uc?export=download&id=1ZuJNuXOyiABSvtnxZHZsIgGlPhM-5alB | G94: =IFERROR(LEFT(RIGHT(H94,LEN(H94)-32),LEN(RIGHT(H94,LEN(H94)-32))-17),"") -> 1ZuJNuXOyiABSvtnxZHZsIgGlPhM-5alB | H94: https://drive.google.com/file/d/1ZuJNuXOyiABSvtnxZHZsIgGlPhM-5alB/view?usp=sharing
B95: 8.2 | C95: =B95&E95 -> 8.2Phon | D95: maɪ ˈsɛl foʊn ɪz aʊt ʌv ˈsɜ:rvɪs naʊ bɪˈkəz aɪ tɜ:rn a:n ði: ˈɛrpleɪn moʊd | E95: Phon | F95: =IF(G95="","","https://docs.google.com/uc?export=download&id="&G95) | G95: =IFERROR(LEFT(RIGHT(H95,LEN(H95)-32),LEN(RIGHT(H95,LEN(H95)-32))-17),"")
A96: 29 | B96: 8.3 | C96: =B96&E96 -> 8.3Viet | D96: Điện thoại của tôi đang nằm ngoài vùng phủ sóng do tôi đang ở trong rừng. | E96: Viet | F96: =IF(G96="","","https://docs.google.com/uc?export=download&id="&G96) | G96: =IFERROR(LEFT(RIGHT(H96,LEN(H96)-32),LEN(RIGHT(H96,LEN(H96)-32))-17),"")
B97: 8.3 | C97: =B97&E97 -> 8.3Eng | D97: My cell phone is out of service now because I am in the forest. | E97: Eng | F97: =IF(G97="","","https://docs.google.com/uc?export=download&id="&G97) -> https://docs.google.com/uc?export=download&id=1_7JRe5nGO6FV7w8kPnCKxZtXxtttTBFG | G97: =IFERROR(LEFT(RIGHT(H97,LEN(H97)-32),LEN(RIGHT(H97,LEN(H97)-32))-17),"") -> 1_7JRe5nGO6FV7w8kPnCKxZtXxtttTBFG | H97: https://drive.google.com/file/d/1_7JRe5nGO6FV7w8kPnCKxZtXxtttTBFG/view?usp=sharing
B98: 8.3 | C98: =B98&E98 -> 8.3Phon | D98: maɪ ˈsɛl foʊn ɪz aʊt ʌv ˈsɜ:rvɪs naʊ bɪˈkəz aɪ æm ɪn ðə ˈfɔ:rɪst | E98: Phon | F98: =IF(G98="","","https://docs.google.com/uc?export=download&id="&G98) | G98: =IFERROR(LEFT(RIGHT(H98,LEN(H98)-32),LEN(RIGHT(H98,LEN(H98)-32))-17),"")
B99: 9 | C99: =B99&E99 -> 9Struc | D99: … TO BE + TOO HEAVY TO BROWSE /… quá nặng để lướt/ | E99: Struc | F99: =IF(G99="","","https://docs.google.com/uc?export=download&id="&G99) | G99: =IFERROR(LEFT(RIGHT(H99,LEN(H99)-32),LEN(RIGHT(H99,LEN(H99)-32))-17),"")
A100: 30 | B100: 9.1 | C100: =B100&E100 -> 9.1Viet | D100: Trang web này quá nặng để lướt. | E100: Viet | F100: =IF(G100="","","https://docs.google.com/uc?export=download&id="&G100) | G100: =IFERROR(LEFT(RIGHT(H100,LEN(H100)-32),LEN(RIGHT(H100,LEN(H100)-32))-17),"")
B101: 9.1 | C101: =B101&E101 -> 9.1Eng | D101: This site is too heavy to browse. | E101: Eng | F101: =IF(G101="","","https://docs.google.com/uc?export=download&id="&G101) -> https://docs.google.com/uc?export=download&id=14zYZl8VbYwuXlwTzBcFxDjgAUwbvM0QZ | G101: =IFERROR(LEFT(RIGHT(H101,LEN(H101)-32),LEN(RIGHT(H101,LEN(H101)-32))-17),"") -> 14zYZl8VbYwuXlwTzBcFxDjgAUwbvM0QZ | H101: https://drive.google.com/file/d/14zYZl8VbYwuXlwTzBcFxDjgAUwbvM0QZ/view?usp=sharing
...

Sheet Viet
B2: Sentence | C2: Link | D2: ID | E2: Copy Google drive to …
B3: 01-05 | C3: =IF(D3="","","https://docs.google.com/uc?export=download&id="&D3) -> https://docs.google.com/uc?export=download&id=1ZZdMGG18yVfo90onhAnTrYOuryrlhC80 | D3: =IFERROR(LEFT(RIGHT(E3,LEN(E3)-32),LEN(RIGHT(E3,LEN(E3)-32))-17),"") -> 1ZZdMGG18yVfo90onhAnTrYOuryrlhC80 | E3: https://drive.google.com/file/d/1ZZdMGG18yVfo90onhAnTrYOuryrlhC80/view?usp=sharing
B4: 05-10 | C4: =IF(D4="","","https://docs.google.com/uc?export=download&id="&D4) -> https://docs.google.com/uc?export=download&id=1z5HXSMVRaPGcSmJJEWFVGBuRIwcQW97u | D4: =IFERROR(LEFT(RIGHT(E4,LEN(E4)-32),LEN(RIGHT(E4,LEN(E4)-32))-17),"") -> 1z5HXSMVRaPGcSmJJEWFVGBuRIwcQW97u | E4: https://drive.google.com/file/d/1z5HXSMVRaPGcSmJJEWFVGBuRIwcQW97u/view?usp=sharing
B5: 11-15 | C5: =IF(D5="","","https://docs.google.com/uc?export=download&id="&D5) -> https://docs.google.com/uc?export=download&id=1bwX6pGLQmxCU8FavAltdLv6E_d3Vkn9o | D5: =IFERROR(LEFT(RIGHT(E5,LEN(E5)-32),LEN(RIGHT(E5,LEN(E5)-32))-17),"") -> 1bwX6pGLQmxCU8FavAltdLv6E_d3Vkn9o | E5: https://drive.google.com/file/d/1bwX6pGLQmxCU8FavAltdLv6E_d3Vkn9o/view?usp=sharing
B6: 16-21 | C6: =IF(D6="","","https://docs.google.com/uc?export=download&id="&D6) -> https://docs.google.com/uc?export=download&id=1X0kc9SnUzzclVGABOwJww-c5yMXqWc2l | D6: =IFERROR(LEFT(RIGHT(E6,LEN(E6)-32),LEN(RIGHT(E6,LEN(E6)-32))-17),"") -> 1X0kc9SnUzzclVGABOwJww-c5yMXqWc2l | E6: https://drive.google.com/file/d/1X0kc9SnUzzclVGABOwJww-c5yMXqWc2l/view?usp=sharing
B7: 01-21 | C7: =IF(D7="","","https://docs.google.com/uc?export=download&id="&D7) -> https://docs.google.com/uc?export=download&id=1M2k6e7nt2w_q4_1QuGCfHDEKs6MDaeAu | D7: =IFERROR(LEFT(RIGHT(E7,LEN(E7)-32),LEN(RIGHT(E7,LEN(E7)-32))-17),"") -> 1M2k6e7nt2w_q4_1QuGCfHDEKs6MDaeAu | E7: https://drive.google.com/file/d/1M2k6e7nt2w_q4_1QuGCfHDEKs6MDaeAu/view?usp=sharing

Sheet Sum
B2: Sentence | D2: Link | E2: ID | F2: Copy Google drive to …
B3: Woman | D3: =IF(E3="","","https://docs.google.com/uc?export=download&id="&E3) -> https://docs.google.com/uc?export=download&id=1rnkrZgzGKWsh4ZfoAd_FuplwYgYY_E1U | E3: =IFERROR(LEFT(RIGHT(F3,LEN(F3)-32),LEN(RIGHT(F3,LEN(F3)-32))-17),"") -> 1rnkrZgzGKWsh4ZfoAd_FuplwYgYY_E1U | F3: https://drive.google.com/file/d/1rnkrZgzGKWsh4ZfoAd_FuplwYgYY_E1U/view?usp=sharing | G3: ="var "&B3&"="""&D3&"""" -> var Woman="https://docs.google.com/uc?export=download&id=1rnkrZgzGKWsh4ZfoAd_FuplwYgYY_E1U"
B4: Man | D4: =IF(E4="","","https://docs.google.com/uc?export=download&id="&E4) -> https://docs.google.com/uc?export=download&id=1IRoMRsshQf-3OlKqKPNoWOshEnQumJp8 | E4: =IFERROR(LEFT(RIGHT(F4,LEN(F4)-32),LEN(RIGHT(F4,LEN(F4)-32))-17),"") -> 1IRoMRsshQf-3OlKqKPNoWOshEnQumJp8 | F4: https://drive.google.com/file/d/1IRoMRsshQf-3OlKqKPNoWOshEnQumJp8/view?usp=sharing | G4: ="var "&B4&"="""&D4&"""" -> var Man="https://docs.google.com/uc?export=download&id=1IRoMRsshQf-3OlKqKPNoWOshEnQumJp8"
B5: Man_01 | C5: Hello everyone. Today I am gonna tell you about the topic of IT life. | D5: =IF(E5="","","https://docs.google.com/uc?export=download&id="&E5) -> https://docs.google.com/uc?export=download&id=1ARjCFfQLtAsXrJYhaxxlI0_8wtKSgkaK | E5: =IFERROR(LEFT(RIGHT(F5,LEN(F5)-32),LEN(RIGHT(F5,LEN(F5)-32))-17),"") -> 1ARjCFfQLtAsXrJYhaxxlI0_8wtKSgkaK | F5: https://drive.google.com/file/d/1ARjCFfQLtAsXrJYhaxxlI0_8wtKSgkaK/view?usp=sharing | G5: ="var "&B5&"="""&D5&"""" -> var Man_01="https://docs.google.com/uc?export=download&id=1ARjCFfQLtAsXrJYhaxxlI0_8wtKSgkaK"
B6: Man_02 | C6: Technology has made my life easier and more enjoyable. | D6: =IF(E6="","","https://docs.google.com/uc?export=download&id="&E6) -> https://docs.google.com/uc?export=download&id=18OIlokL_Ypf0kd9Pb2Pk7B9SV4VAfzOq | E6: =IFERROR(LEFT(RIGHT(F6,LEN(F6)-32),LEN(RIGHT(F6,LEN(F6)-32))-17),"") -> 18OIlokL_Ypf0kd9Pb2Pk7B9SV4VAfzOq | F6: https://drive.google.com/file/d/18OIlokL_Ypf0kd9Pb2Pk7B9SV4VAfzOq/view?usp=sharing | G6: ="var "&B6&"="""&D6&"""" -> var Man_02="https://docs.google.com/uc?export=download&id=18OIlokL_Ypf0kd9Pb2Pk7B9SV4VAfzOq"
B7: Man_03 | C7: I couldn't live without technological products. | D7: =IF(E7="","","https://docs.google.com/uc?export=download&id="&E7) -> https://docs.google.com/uc?export=download&id=1U8yAtihPxEQFDFLXhZx1tQx5rsEWx2-I | E7: =IFERROR(LEFT(RIGHT(F7,LEN(F7)-32),LEN(RIGHT(F7,LEN(F7)-32))-17),"") -> 1U8yAtihPxEQFDFLXhZx1tQx5rsEWx2-I | F7: https://drive.google.com/file/d/1U8yAtihPxEQFDFLXhZx1tQx5rsEWx2-I/view?usp=sharing | G7: ="var "&B7&"="""&D7&"""" -> var Man_03="https://docs.google.com/uc?export=download&id=1U8yAtihPxEQFDFLXhZx1tQx5rsEWx2-I"
B8: Man_04 | C8: I also couldn't live without my smartphone. | D8: =IF(E8="","","https://docs.google.com/uc?export=download&id="&E8) -> https://docs.google.com/uc?export=download&id=1OiabGRSfr7nPI_-OYVpmCXbor_6gtLg4 | E8: =IFERROR(LEFT(RIGHT(F8,LEN(F8)-32),LEN(RIGHT(F8,LEN(F8)-32))-17),"") -> 1OiabGRSfr7nPI_-OYVpmCXbor_6gtLg4 | F8: https://drive.google.com/file/d/1OiabGRSfr7nPI_-OYVpmCXbor_6gtLg4/view?usp=sharing | G8: ="var "&B8&"="""&D8&"""" -> var Man_04="https://docs.google.com/uc?export=download&id=1OiabGRSfr7nPI_-OYVpmCXbor_6gtLg4"
B9: Man_05 | C9: I recharge my cell phone twice a day. | D9: =IF(E9="","","https://docs.google.com/uc?export=download&id="&E9) -> https://docs.google.com/uc?export=download&id=1VogOhpIHAXlNqfB9gn9E4iwR95jwMDcL | E9: =IFERROR(LEFT(RIGHT(F9,LEN(F9)-32),LEN(RIGHT(F9,LEN(F9)-32))-17),"") -> 1VogOhpIHAXlNqfB9gn9E4iwR95jwMDcL | F9: https://drive.google.com/file/d/1VogOhpIHAXlNqfB9gn9E4iwR95jwMDcL/view?usp=sharing | G9: ="var "&B9&"="""&D9&"""" -> var Man_05="https://docs.google.com/uc?export=download&id=1VogOhpIHAXlNqfB9gn9E4iwR95jwMDcL"
B10: Man_06 | C10: I access the social networks on my smartphone. | D10: =IF(E10="","","https://docs.google.com/uc?export=download&id="&E10) -> https://docs.google.com/uc?export=download&id=1SegxPfljaDh7YlB-oUibsUWYGJf1bq71 | E10: =IFERROR(LEFT(RIGHT(F10,LEN(F10)-32),LEN(RIGHT(F10,LEN(F10)-32))-17),"") -> 1SegxPfljaDh7YlB-oUibsUWYGJf1bq71 | F10: https://drive.google.com/file/d/1SegxPfljaDh7YlB-oUibsUWYGJf1bq71/view?usp=sharing | G10: ="var "&B10&"="""&D10&"""" -> var Man_06="https://docs.google.com/uc?export=download&id=1SegxPfljaDh7YlB-oUibsUWYGJf1bq71"
B11: Man_07 | C11: Facebook is one of the most popular websites in the world, with millions of users in different countries. | D11: =IF(E11="","","https://docs.google.com/uc?export=download&id="&E11) -> https://docs.google.com/uc?export=download&id=1f5c9Aukq6Zp5QX7WWbldt7ijgjC1tOrl | E11: =IFERROR(LEFT(RIGHT(F11,LEN(F11)-32),LEN(RIGHT(F11,LEN(F11)-32))-17),"") -> 1f5c9Aukq6Zp5QX7WWbldt7ijgjC1tOrl | F11: https://drive.google.com/file/d/1f5c9Aukq6Zp5QX7WWbldt7ijgjC1tOrl/view?usp=sharing | G11: ="var "&B11&"="""&D11&"""" -> var Man_07="https://docs.google.com/uc?export=download&id=1f5c9Aukq6Zp5QX7WWbldt7ijgjC1tOrl"
B12: Man_08 | C12: I've updated my status every week. | D12: =IF(E12="","","https://docs.google.com/uc?export=download&id="&E12) -> https://docs.google.com/uc?export=download&id=1flH1KfEmwA2RKRC_O7kAzTUwM_OXvFQm | E12: =IFERROR(LEFT(RIGHT(F12,LEN(F12)-32),LEN(RIGHT(F12,LEN(F12)-32))-17),"") -> 1flH1KfEmwA2RKRC_O7kAzTUwM_OXvFQm | F12: https://drive.google.com/file/d/1flH1KfEmwA2RKRC_O7kAzTUwM_OXvFQm/view?usp=sharing | G12: ="var "&B12&"="""&D12&"""" -> var Man_08="https://docs.google.com/uc?export=download&id=1flH1KfEmwA2RKRC_O7kAzTUwM_OXvFQm"
B13: Man_09 | C13: I can study, go shopping online, connect with my friends, and stay up-to-date with news and current events via Facebook. | D13: =IF(E13="","","https://docs.google.com/uc?export=download&id="&E13) -> https://docs.google.com/uc?export=download&id=1Qmq_IgGi8Hxt-vz7ZX4F7Q6NfSlQ_hbA | E13: =IFERROR(LEFT(RIGHT(F13,LEN(F13)-32),LEN(RIGHT(F13,LEN(F13)-32))-17),"") -> 1Qmq_IgGi8Hxt-vz7ZX4F7Q6NfSlQ_hbA | F13: https://drive.google.com/file/d/1Qmq_IgGi8Hxt-vz7ZX4F7Q6NfSlQ_hbA/view?usp=sharing | G13: ="var "&B13&"="""&D13&"""" -> var Man_09="https://docs.google.com/uc?export=download&id=1Qmq_IgGi8Hxt-vz7ZX4F7Q6NfSlQ_hbA"
B14: Man_10 | C14: Besides, YouTube is a website that I find very useful for me. | D14: =IF(E14="","","https://docs.google.com/uc?export=download&id="&E14) -> https://docs.google.com/uc?export=download&id=1AaqzPkHBzS5kSmpKn1DNq1Nta9rq0LE6 | E14: =IFERROR(LEFT(RIGHT(F14,LEN(F14)-32),LEN(RIGHT(F14,LEN(F14)-32))-17),"") -> 1AaqzPkHBzS5kSmpKn1DNq1Nta9rq0LE6 | F14: https://drive.google.com/file/d/1AaqzPkHBzS5kSmpKn1DNq1Nta9rq0LE6/view?usp=sharing | G14: ="var "&B14&"="""&D14&"""" -> var Man_10="https://docs.google.com/uc?export=download&id=1AaqzPkHBzS5kSmpKn1DNq1Nta9rq0LE6"
B15: Man_11 | C15: New videos have been uploaded onto YouTube every day. | D15: =IF(E15="","","https://docs.google.com/uc?export=download&id="&E15) -> https://docs.google.com/uc?export=download&id=1tVCy1Jeos1g99jAgojFikj4-lZ-Q8RIu | E15: =IFERROR(LEFT(RIGHT(F15,LEN(F15)-32),LEN(RIGHT(F15,LEN(F15)-32))-17),"") -> 1tVCy1Jeos1g99jAgojFikj4-lZ-Q8RIu | F15: https://drive.google.com/file/d/1tVCy1Jeos1g99jAgojFikj4-lZ-Q8RIu/view?usp=sharing | G15: ="var "&B15&"="""&D15&"""" -> var Man_11="https://docs.google.com/uc?export=download&id=1tVCy1Jeos1g99jAgojFikj4-lZ-Q8RIu"
B16: Man_12 | C16: I also record videos on my smartphone and upload them onto YouTube. | D16: =IF(E16="","","https://docs.google.com/uc?export=download&id="&E16) -> https://docs.google.com/uc?export=download&id=1koIXL8qrd_kpsIOviWJKoyH-1rDUfu5C | E16: =IFERROR(LEFT(RIGHT(F16,LEN(F16)-32),LEN(RIGHT(F16,LEN(F16)-32))-17),"") -> 1koIXL8qrd_kpsIOviWJKoyH-1rDUfu5C | F16: https://drive.google.com/file/d/1koIXL8qrd_kpsIOviWJKoyH-1rDUfu5C/view?usp=sharing | G16: ="var "&B16&"="""&D16&"""" -> var Man_12="https://docs.google.com/uc?export=download&id=1koIXL8qrd_kpsIOviWJKoyH-1rDUfu5C"
... B19: Man_15 | C19: Thanks for listening! | D19: =IF(E19="","","https://docs.google.com/uc?export=download&id="&E19) -> https://docs.google.com/uc?export=download&id=1V2DxEk-RqREkbDD4qSRzxsw8s8-oCXQO | E19: =IFERROR(LEFT(RIGHT(F19,LEN(F19)-32),LEN(RIGHT(F19,LEN(F19)-32))-17),"") -> 1V2DxEk-RqREkbDD4qSRzxsw8s8-oCXQO | F19: https://drive.google.com/file/d/1V2DxEk-RqREkbDD4qSRzxsw8s8-oCXQO/view?usp=sharing | G19: ="var "&B19&"="""&D19&"""" -> var Man_15="https://docs.google.com/uc?export=download&id=1V2DxEk-RqREkbDD4qSRzxsw8s8-oCXQO"

Sheet Ramdom
B1: From | C1: 1
B2: To | C2: 49
C3: No | D3: No | E3: Viet | F3: Eng
A4: =C1 -> 1 | B4: =IF(A4="","",RANDBETWEEN($C$1,$C$2)) -> 9 | C4: =IFERROR($C$1-1+_xlfn.RANK.EQ(B4,$B$4:$B$78)+COUNTIF(B$4:$B4,B4)-1,"") -> 37 | D4: =IFERROR(VLOOKUP(C4,'The IT Life'!A:B,2,0),"") -> 11.1 | E4: =IFERROR(VLOOKUP(D4&"Viet",'The IT Life'!C:D,2,0),"") -> Video mới của ban nhạc tôi yêu thích được đăng tải lên youtube. | F4: =IFERROR(VLOOKUP(D4&"Eng",'The IT Life'!C:D,2,0),"") -> A new video of my favorite band has been uploaded onto youtube.
A5: =IFERROR(IF(A4+1>$C$2,"",A4+1),"") -> 2 | B5: =IF(A5="","",RANDBETWEEN($C$1,$C$2)) -> 38 | C5: =IFERROR($C$1-1+_xlfn.RANK.EQ(B5,$B$4:$B$78)+COUNTIF(B$4:$B5,B5)-1,"") -> 7 | D5: =IFERROR(VLOOKUP(C5,'The IT Life'!A:B,2,0),"") -> 2.3 | E5: =IFERROR(VLOOKUP(D5&"Viet",'The IT Life'!C:D,2,0),"") -> Tôi sạc pin điện thoại của mình 2 lần 1 ngày. | F5: =IFERROR(VLOOKUP(D5&"Eng",'The IT Life'!C:D,2,0),"") -> I recharge my cell phone twice a day.
A6: =IFERROR(IF(A5+1>$C$2,"",A5+1),"") -> 3 | B6: =IF(A6="","",RANDBETWEEN($C$1,$C$2)) -> 32 | C6: =IFERROR($C$1-1+_xlfn.RANK.EQ(B6,$B$4:$B$78)+COUNTIF(B$4:$B6,B6)-1,"") -> 18 | D6: =IFERROR(VLOOKUP(C6,'The IT Life'!A:B,2,0),"") -> 5.3 | E6: =IFERROR(VLOOKUP(D6&"Viet",'The IT Life'!C:D,2,0),"") -> Tôi trả lời một bình luận. | F6: =IFERROR(VLOOKUP(D6&"Eng",'The IT Life'!C:D,2,0),"") -> I respond to a comment.
A7: =IFERROR(IF(A6+1>$C$2,"",A6+1),"") -> 4 | B7: =IF(A7="","",RANDBETWEEN($C$1,$C$2)) -> 48 | C7: =IFERROR($C$1-1+_xlfn.RANK.EQ(B7,$B$4:$B$78)+COUNTIF(B$4:$B7,B7)-1,"") -> 3 | D7: =IFERROR(VLOOKUP(C7,'The IT Life'!A:B,2,0),"") -> 1.3 | E7: =IFERROR(VLOOKUP(D7&"Viet",'The IT Life'!C:D,2,0),"") -> Tôi chỉnh điện thoại sang chế độ ban đêm. | F7: =IFERROR(VLOOKUP(D7&"Eng",'The IT Life'!C:D,2,0),"") -> I set my cell phone to night mode.
A8: =IFERROR(IF(A7+1>$C$2,"",A7+1),"") -> 5 | B8: =IF(A8="","",RANDBETWEEN($C$1,$C$2)) -> 15 | C8: =IFERROR($C$1-1+_xlfn.RANK.EQ(B8,$B$4:$B$78)+COUNTIF(B$4:$B8,B8)-1,"") -> 31 | D8: =IFERROR(VLOOKUP(C8,'The IT Life'!A:B,2,0),"") -> 9.2 | E8: =IFERROR(VLOOKUP(D8&"Viet",'The IT Life'!C:D,2,0),"") -> Youtube quá nặng để lướt. | F8: =IFERROR(VLOOKUP(D8&"Eng",'The IT Life'!C:D,2,0),"") -> Youtube is too heavy to browse.
A9: =IFERROR(IF(A8+1>$C$2,"",A8+1),"") -> 6 | B9: =IF(A9="","",RANDBETWEEN($C$1,$C$2)) -> 26 | C9: =IFERROR($C$1-1+_xlfn.RANK.EQ(B9,$B$4:$B$78)+COUNTIF(B$4:$B9,B9)-1,"") -> 25 | D9: =IFERROR(VLOOKUP(C9,'The IT Life'!A:B,2,0),"") -> 7.3 | E9: =IFERROR(VLOOKUP(D9&"Viet",'The IT Life'!C:D,2,0),"") -> Tôi dùng điện thoại để kết nối internet. | F9: =IFERROR(VLOOKUP(D9&"Eng",'The IT Life'!C:D,2,0),"") -> I use my phone to access the internet.
A10: =IFERROR(IF(A9+1>$C$2,"",A9+1),"") -> 7 | B10: =IF(A10="","",RANDBETWEEN($C$1,$C$2)) -> 22 | C10: =IFERROR($C$1-1+_xlfn.RANK.EQ(B10,$B$4:$B$78)+COUNTIF(B$4:$B10,B10)-1,"") -> 27 | D10: =IFERROR(VLOOKUP(C10,'The IT Life'!A:B,2,0),"") -> 8.1 | E10: =IFERROR(VLOOKUP(D10&"Viet",'The IT Life'!C:D,2,0),"") -> Điện thoại của tôi đang nằm ngoài vùng phủ sóng do tôi đang ở trong tầng hầm. | F10: =IFERROR(VLOOKUP(D10&"Eng",'The IT Life'!C:D,2,0),"") -> My cell phone is out of service now because I’m in the basement.
A11: =IFERROR(IF(A10+1>$C$2,"",A10+1),"") -> 8 | B11: =IF(A11="","",RANDBETWEEN($C$1,$C$2)) -> 33 | C11: =IFERROR($C$1-1+_xlfn.RANK.EQ(B11,$B$4:$B$78)+COUNTIF(B$4:$B11,B11)-1,"") -> 17 | D11: =IFERROR(VLOOKUP(C11,'The IT Life'!A:B,2,0),"") -> 5.2 | E11: =IFERROR(VLOOKUP(D11&"Viet",'The IT Life'!C:D,2,0),"") -> Tôi trả lời một email. | F11: =IFERROR(VLOOKUP(D11&"Eng",'The IT Life'!C:D,2,0),"") -> I respond to an email.
A12: =IFERROR(IF(A11+1>$C$2,"",A11+1),"") -> 9 | B12: =IF(A12="","",RANDBETWEEN($C$1,$C$2)) -> 28 | C12: =IFERROR($C$1-1+_xlfn.RANK.EQ(B12,$B$4:$B$78)+COUNTIF(B$4:$B12,B12)-1,"") -> 23 | D12: =IFERROR(VLOOKUP(C12,'The IT Life'!A:B,2,0),"") -> 7.1 | E12: =IFERROR(VLOOKUP(D12&"Viet",'The IT Life'!C:D,2,0),"") -> Tôi dùng điện thoại để gọi điện. | F12: =IFERROR(VLOOKUP(D12&"Eng",'The IT Life'!C:D,2,0),"") -> I use my phone to make a phone call.
A13: =IFERROR(IF(A12+1>$C$2,"",A12+1),"") -> 10 | B13: =IF(A13="","",RANDBETWEEN($C$1,$C$2)) -> 18 | C13: =IFERROR($C$1-1+_xlfn.RANK.EQ(B13,$B$4:$B$78)+COUNTIF(B$4:$B13,B13)-1,"") -> 29 | D13: =IFERROR(VLOOKUP(C13,'The IT Life'!A:B,2,0),"") -> 8.3 | E13: =IFERROR(VLOOKUP(D13&"Viet",'The IT Life'!C:D,2,0),"") -> Điện thoại của tôi đang nằm ngoài vùng phủ sóng do tôi đang ở trong rừng. | F13: =IFERROR(VLOOKUP(D13&"Eng",'The IT Life'!C:D,2,0),"") -> My cell phone is out of service now because I am in the forest. | J13: ;'
A14: =IFERROR(IF(A13+1>$C$2,"",A13+1),"") -> 11 | B14: =IF(A14="","",RANDBETWEEN($C$1,$C$2)) -> 5 | C14: =IFERROR($C$1-1+_xlfn.RANK.EQ(B14,$B$4:$B$78)+COUNTIF(B$4:$B14,B14)-1,"") -> 41 | D14: =IFERROR(VLOOKUP(C14,'The IT Life'!A:B,2,0),"") -> 12.1 | E14: =IFERROR(VLOOKUP(D14&"Viet",'The IT Life'!C:D,2,0),"") -> Tôi có thể làm việc thông qua facebook. | F14: =IFERROR(VLOOKUP(D14&"Eng",'The IT Life'!C:D,2,0),"") -> I can work via facebook.
A15: =IFERROR(IF(A14+1>$C$2,"",A14+1),"") -> 12 | B15: =IF(A15="","",RANDBETWEEN($C$1,$C$2)) -> 49 | C15: =IFERROR($C$1-1+_xlfn.RANK.EQ(B15,$B$4:$B$78)+COUNTIF(B$4:$B15,B15)-1,"") -> 1 | D15: =IFERROR(VLOOKUP(C15,'The IT Life'!A:B,2,0),"") -> 1.1 | E15: =IFERROR(VLOOKUP(D15&"Viet",'The IT Life'!C:D,2,0),"") -> Tôi chỉnh điện thoại sang chế độ yên lặng. | F15: =IFERROR(VLOOKUP(D15&"Eng",'The IT Life'!C:D,2,0),"") -> I set my cell phone to silent mode. | J15: lkkj
A16: =IFERROR(IF(A15+1>$C$2,"",A15+1),"") -> 13 | B16: =IF(A16="","",RANDBETWEEN($C$1,$C$2)) -> 35 | C16: =IFERROR($C$1-1+_xlfn.RANK.EQ(B16,$B$4:$B$78)+COUNTIF(B$4:$B16,B16)-1,"") -> 13 | D16: =IFERROR(VLOOKUP(C16,'The IT Life'!A:B,2,0),"") -> 4.2 | E16: =IFERROR(VLOOKUP(D16&"Viet",'The IT Life'!C:D,2,0),"") -> Tôi quay phim bằng camera điện thoại rồi gửi đi. | F16: =IFERROR(VLOOKUP(D16&"Eng",'The IT Life'!C:D,2,0),"") -> I record a video with my cell phone and send it.
A17: =IFERROR(IF(A16+1>$C$2,"",A16+1),"") -> 14 | B17: =IF(A17="","",RANDBETWEEN($C$1,$C$2)) -> 38 | C17: =IFERROR($C$1-1+_xlfn.RANK.EQ(B17,$B$4:$B$78)+COUNTIF(B$4:$B17,B17)-1,"") -> 8 | D17: =IFERROR(VLOOKUP(C17,'The IT Life'!A:B,2,0),"") -> 3.1 | E17: =IFERROR(VLOOKUP(D17&"Viet",'The IT Life'!C:D,2,0),"") -> Tôi kết nối máy in với máy tính. | F17: =IFERROR(VLOOKUP(D17&"Eng",'The IT Life'!C:D,2,0),"") -> I connect the printer to the computer.
A18: =IFERROR(IF(A17+1>$C$2,"",A17+1),"") -> 15 | B18: =IF(A18="","",RANDBETWEEN($C$1,$C$2)) -> 45 | C18: =IFERROR($C$1-1+_xlfn.RANK.EQ(B18,$B$4:$B$78)+COUNTIF(B$4:$B18,B18)-1,"") -> 4 | D18: =IFERROR(VLOOKUP(C18,'The IT Life'!A:B,2,0),"") -> 1.4 | E18: =IFERROR(VLOOKUP(D18&"Viet",'The IT Life'!C:D,2,0),"") -> Tôi chỉnh điện thoại sang chế độ phòng họp. | F18: =IFERROR(VLOOKUP(D18&"Eng",'The IT Life'!C:D,2,0),"") -> I set my cell phone to meeting mode.
A19: =IFERROR(IF(A18+1>$C$2,"",A18+1),"") -> 16 | B19: =IF(A19="","",RANDBETWEEN($C$1,$C$2)) -> 49 | C19: =IFERROR($C$1-1+_xlfn.RANK.EQ(B19,$B$4:$B$78)+COUNTIF(B$4:$B19,B19)-1,"") -> 2 | D19: =IFERROR(VLOOKUP(C19,'The IT Life'!A:B,2,0),"") -> 1.2 | E19: =IFERROR(VLOOKUP(D19&"Viet",'The IT Life'!C:D,2,0),"") -> Tôi chỉnh điện thoại sang chế độ máy bay. | F19: =IFERROR(VLOOKUP(D19&"Eng",'The IT Life'!C:D,2,0),"") -> I set my cell phone to airplane mode.
A20: =IFERROR(IF(A19+1>$C$2,"",A19+1),"") -> 17 | B20: =IF(A20="","",RANDBETWEEN($C$1,$C$2)) -> 29 | C20: =IFERROR($C$1-1+_xlfn.RANK.EQ(B20,$B$4:$B$78)+COUNTIF(B$4:$B20,B20)-1,"") -> 22 | D20: =IFERROR(VLOOKUP(C20,'The IT Life'!A:B,2,0),"") -> 6.4 | E20: =IFERROR(VLOOKUP(D20&"Viet",'The IT Life'!C:D,2,0),"") -> Tôi đặt một đường link trong phần mô tả của mình. | F20: =IFERROR(VLOOKUP(D20&"Eng",'The IT Life'!C:D,2,0),"") -> I put a link in my description.
A21: =IFERROR(IF(A20+1>$C$2,"",A20+1),"") -> 18 | B21: =IF(A21="","",RANDBETWEEN($C$1,$C$2)) -> 32 | C21: =IFERROR($C$1-1+_xlfn.RANK.EQ(B21,$B$4:$B$78)+COUNTIF(B$4:$B21,B21)-1,"") -> 19 | D21: =IFERROR(VLOOKUP(C21,'The IT Life'!A:B,2,0),"") -> 6.1 | E21: =IFERROR(VLOOKUP(D21&"Viet",'The IT Life'!C:D,2,0),"") -> Tôi đặt một đường link trong bài đăng của mình. | F21: =IFERROR(VLOOKUP(D21&"Eng",'The IT Life'!C:D,2,0),"") -> I put a link in my post.
A22: =IFERROR(IF(A21+1>$C$2,"",A21+1),"") -> 19 | B22: =IF(A22="","",RANDBETWEEN($C$1,$C$2)) -> 37 | C22: =IFERROR($C$1-1+_xlfn.RANK.EQ(B22,$B$4:$B$78)+COUNTIF(B$4:$B22,B22)-1,"") -> 10 | D22: =IFERROR(VLOOKUP(C22,'The IT Life'!A:B,2,0),"") -> 3.3 | E22: =IFERROR(VLOOKUP(D22&"Viet",'The IT Life'!C:D,2,0),"") -> Tôi kết nối điện thoại với máy tính. | F22: =IFERROR(VLOOKUP(D22&"Eng",'The IT Life'!C:D,2,0),"") -> I connect my smartphone to the computer.
A23: =IFERROR(IF(A22+1>$C$2,"",A22+1),"") -> 20 | B23: =IF(A23="","",RANDBETWEEN($C$1,$C$2)) -> 32 | C23: =IFERROR($C$1-1+_xlfn.RANK.EQ(B23,$B$4:$B$78)+COUNTIF(B$4:$B23,B23)-1,"") -> 20 | D23: =IFERROR(VLOOKUP(C23,'The IT Life'!A:B,2,0),"") -> 6.2 | E23: =IFERROR(VLOOKUP(D23&"Viet",'The IT Life'!C:D,2,0),"") -> Tôi đặt một đường link trong hình ảnh của mình. | F23: =IFERROR(VLOOKUP(D23&"Eng",'The IT Life'!C:D,2,0),"") -> I put a link in my image.
A24: =IFERROR(IF(A23+1>$C$2,"",A23+1),"") -> 21 | B24: =IF(A24="","",RANDBETWEEN($C$1,$C$2)) -> 2 | C24: =IFERROR($C$1-1+_xlfn.RANK.EQ(B24,$B$4:$B$78)+COUNTIF(B$4:$B24,B24)-1,"") -> 46 | D24: =IFERROR(VLOOKUP(C24,'The IT Life'!A:B,2,0),"") -> 13.1 | E24: =IFERROR(VLOOKUP(D24&"Viet",'The IT Life'!C:D,2,0),"") -> Công nghệ làm cho đời sống của tôi dễ dàng hơn. | F24: =IFERROR(VLOOKUP(D24&"Eng",'The IT Life'!C:D,2,0),"") -> Technology has made my life easier.
A25: =IFERROR(IF(A24+1>$C$2,"",A24+1),"") -> 22 | B25: =IF(A25="","",RANDBETWEEN($C$1,$C$2)) -> 35 | C25: =IFERROR($C$1-1+_xlfn.RANK.EQ(B25,$B$4:$B$78)+COUNTIF(B$4:$B25,B25)-1,"") -> 14 | D25: =IFERROR(VLOOKUP(C25,'The IT Life'!A:B,2,0),"") -> 4.3 | E25: =IFERROR(VLOOKUP(D25&"Viet",'The IT Life'!C:D,2,0),"") -> Tôi đánh một tin nhắn bằng điện thoại rồi gửi đi. | F25: =IFERROR(VLOOKUP(D25&"Eng",'The IT Life'!C:D,2,0),"") -> I text a message with my cell phone and send it.
A26: =IFERROR(IF(A25+1>$C$2,"",A25+1),"") -> 23 | B26: =IF(A26="","",RANDBETWEEN($C$1,$C$2)) -> 3 | C26: =IFERROR($C$1-1+_xlfn.RANK.EQ(B26,$B$4:$B$78)+COUNTIF(B$4:$B26,B26)-1,"") -> 45 | D26: =IFERROR(VLOOKUP(C26,'The IT Life'!A:B,2,0),"") -> 12.5 | E26: =IFERROR(VLOOKUP(D26&"Viet",'The IT Life'!C:D,2,0),"") -> Tôi có thể cập nhật tin tức và sự kiện đang diễn ra thông qua facebook. | F26: =IFERROR(VLOOKUP(D26&"Eng",'The IT Life'!C:D,2,0),"") -> I stay up-to-date with news and current events via facebook.
A27: =IFERROR(IF(A26+1>$C$2,"",A26+1),"") -> 24 | B27: =IF(A27="","",RANDBETWEEN($C$1,$C$2)) -> 21 | C27: =IFERROR($C$1-1+_xlfn.RANK.EQ(B27,$B$4:$B$78)+COUNTIF(B$4:$B27,B27)-1,"") -> 28 | D27: =IFERROR(VLOOKUP(C27,'The IT Life'!A:B,2,0),"") -> 8.2 | E27: =IFERROR(VLOOKUP(D27&"Viet",'The IT Life'!C:D,2,0),"") -> Điện thoại của tôi đang nằm ngoài vùng phủ sóng do tôi đang bật chế độ máy bay. | F27: =IFERROR(VLOOKUP(D27&"Eng",'The IT Life'!C:D,2,0),"") -> My cell phone is out of service now because I turn on the airplane mode.
... A72: =IFERROR(IF(A71+1>$C$2,"",A71+1),"") | B72: =IF(A72="","",RANDBETWEEN($C$1,$C$2)) | C72: =IFERROR($C$1-1+_xlfn.RANK.EQ(B72,$B$4:$B$78)+COUNTIF(B$4:$B72,B72)-1,"") | D72: =IFERROR(VLOOKUP(C72,'The IT Life'!A:B,2,0),"") | E72: =IFERROR(VLOOKUP(D72&"Viet",'The IT Life'!C:D,2,0),"") | F72: =IFERROR(VLOOKUP(D72&"Eng",'The IT Life'!C:D,2,0),"")
A73: =IFERROR(IF(A72+1>$C$2,"",A72+1),"") | B73: =IF(A73="","",RANDBETWEEN($C$1,$C$2)) | C73: =IFERROR($C$1-1+_xlfn.RANK.EQ(B73,$B$4:$B$78)+COUNTIF(B$4:$B73,B73)-1,"") | D73: =IFERROR(VLOOKUP(C73,'The IT Life'!A:B,2,0),"")
A74: =IFERROR(IF(A73+1>$C$2,"",A73+1),"") | B74: =IF(A74="","",RANDBETWEEN($C$1,$C$2)) | C74: =IFERROR($C$1-1+_xlfn.RANK.EQ(B74,$B$4:$B$78)+COUNTIF(B$4:$B74,B74)-1,"") | D74: =IFERROR(VLOOKUP(C74,'The IT Life'!A:B,2,0),"")
A75: =IFERROR(IF(A74+1>$C$2,"",A74+1),"") | B75: =IF(A75="","",RANDBETWEEN($C$1,$C$2)) | C75: =IFERROR($C$1-1+_xlfn.RANK.EQ(B75,$B$4:$B$78)+COUNTIF(B$4:$B75,B75)-1,"") | D75: =IFERROR(VLOOKUP(C75,'The IT Life'!A:B,2,0),"")
A76: =IFERROR(IF(A75+1>$C$2,"",A75+1),"") | B76: =IF(A76="","",RANDBETWEEN($C$1,$C$2)) | C76: =IFERROR($C$1-1+_xlfn.RANK.EQ(B76,$B$4:$B$78)+COUNTIF(B$4:$B76,B76)-1,"") | D76: =IFERROR(VLOOKUP(C76,'The IT Life'!A:B,2,0),"")
A77: =IFERROR(IF(A76+1>$C$2,"",A76+1),"") | B77: =IF(A77="","",RANDBETWEEN($C$1,$C$2)) | C77: =IFERROR($C$1-1+_xlfn.RANK.EQ(B77,$B$4:$B$78)+COUNTIF(B$4:$B77,B77)-1,"") | D77: =IFERROR(VLOOKUP(C77,'The IT Life'!A:B,2,0),"")
A78: =IFERROR(IF(A77+1>$C$2,"",A77+1),"") | B78: =IF(A78="","",RANDBETWEEN($C$1,$C$2)) | C78: =IFERROR($C$1-1+_xlfn.RANK.EQ(B78,$B$4:$B$78)+COUNTIF(B$4:$B78,B78)-1,"") | D78: =IFERROR(VLOOKUP(C78,'The IT Life'!A:B,2,0),"")
A79: =IFERROR(IF(A78+1>$C$2,"",A78+1),"") | B79: =IF(A79="","",RANDBETWEEN($C$1,$C$2)) | C79: =IFERROR($C$1-1+_xlfn.RANK.EQ(B79,$B$4:$B$78)+COUNTIF(B$4:$B79,B79)-1,"") | D79: =IFERROR(VLOOKUP(C79,'The IT Life'!A:B,2,0),"")
A80: =IFERROR(IF(A79+1>$C$2,"",A79+1),"") | B80: =IF(A80="","",RANDBETWEEN($C$1,$C$2)) | C80: =IFERROR($C$1-1+_xlfn.RANK.EQ(B80,$B$4:$B$78)+COUNTIF(B$4:$B80,B80)-1,"") | D80: =IFERROR(VLOOKUP(C80,'The IT Life'!A:B,2,0),"")
A81: =IFERROR(IF(A80+1>$C$2,"",A80+1),"") | B81: =IF(A81="","",RANDBETWEEN($C$1,$C$2)) | C81: =IFERROR($C$1-1+_xlfn.RANK.EQ(B81,$B$4:$B$78)+COUNTIF(B$4:$B81,B81)-1,"") | D81: =IFERROR(VLOOKUP(C81,'The IT Life'!A:B,2,0),"")
A82: =IFERROR(IF(A81+1>$C$2,"",A81+1),"") | B82: =IF(A82="","",RANDBETWEEN($C$1,$C$2)) | C82: =IFERROR($C$1-1+_xlfn.RANK.EQ(B82,$B$4:$B$78)+COUNTIF(B$4:$B82,B82)-1,"") | D82: =IFERROR(VLOOKUP(C82,'The IT Life'!A:B,2,0),"")
A83: =IFERROR(IF(A82+1>$C$2,"",A82+1),"") | B83: =IF(A83="","",RANDBETWEEN($C$1,$C$2)) | C83: =IFERROR($C$1-1+_xlfn.RANK.EQ(B83,$B$4:$B$78)+COUNTIF(B$4:$B83,B83)-1,"") | D83: =IFERROR(VLOOKUP(C83,'The IT Life'!A:B,2,0),"")
A84: =IFERROR(IF(A83+1>$C$2,"",A83+1),"") | B84: =IF(A84="","",RANDBETWEEN($C$1,$C$2)) | C84: =IFERROR($C$1-1+_xlfn.RANK.EQ(B84,$B$4:$B$78)+COUNTIF(B$4:$B84,B84)-1,"") | D84: =IFERROR(VLOOKUP(C84,'The IT Life'!A:B,2,0),"")
... A142: =IFERROR(IF(A141+1>$C$2,"",A141+1),"") | B142: =IF(A142="","",RANDBETWEEN($C$1,$C$2)) | C142: =IFERROR($C$1-1+_xlfn.RANK.EQ(B142,$B$4:$B$78)+COUNTIF(B$4:$B142,B142)-1,"") | D142: =IFERROR(VLOOKUP(C142,'The IT Life'!A:B,2,0),"")
A143: =IFERROR(IF(A142+1>$C$2,"",A142+1),"") | B143: =IF(A143="","",RANDBETWEEN($C$1,$C$2))
A144: =IFERROR(IF(A143+1>$C$2,"",A143+1),"") | B144: =IF(A144="","",RANDBETWEEN($C$1,$C$2))
A145: =IFERROR(IF(A144+1>$C$2,"",A144+1),"") | B145: =IF(A145="","",RANDBETWEEN($C$1,$C$2))
A146: =IFERROR(IF(A145+1>$C$2,"",A145+1),"") | B146: =IF(A146="","",RANDBETWEEN($C$1,$C$2))
A147: =IFERROR(IF(A146+1>$C$2,"",A146+1),"") | B147: =IF(A147="","",RANDBETWEEN($C$1,$C$2))
A148: =IFERROR(IF(A147+1>$C$2,"",A147+1),"") | B148: =IF(A148="","",RANDBETWEEN($C$1,$C$2))
A149: =IFERROR(IF(A148+1>$C$2,"",A148+1),"") | B149: =IF(A149="","",RANDBETWEEN($C$1,$C$2))
A150: =IFERROR(IF(A149+1>$C$2,"",A149+1),"") | B150: =IF(A150="","",RANDBETWEEN($C$1,$C$2))
A151: =IFERROR(IF(A150+1>$C$2,"",A150+1),"") | B151: =IF(A151="","",RANDBETWEEN($C$1,$C$2))
A152: =IFERROR(IF(A151+1>$C$2,"",A151+1),"") | B152: =IF(A152="","",RANDBETWEEN($C$1,$C$2))
A153: =IFERROR(IF(A152+1>$C$2,"",A152+1),"") | B153: =IF(A153="","",RANDBETWEEN($C$1,$C$2))
A154: =IFERROR(IF(A153+1>$C$2,"",A153+1),"") | B154: =IF(A154="","",RANDBETWEEN($C$1,$C$2))
... A295: =IFERROR(IF(A294+1>$C$2,"",A294+1),"") | B295: =IF(A295="","",RANDBETWEEN($C$1,$C$2))

Sheet Sheet1
A1: dưq | B1: eqwe
A2: 1 | B2: I use my phone to send messages.
A3: 2 | B3: My cell phone is out of service now because I turn on the airplane mode.
A4: 3 | B4: My Tam’s photos have been uploaded on her fanpage.
A5: 4 | B5: This music site is too heavy to browse.
A6: 5 | B6: I’ve updated this page during my business trip.
A7: 6 | B7: I use my phone to access the internet.
A8: 7 | B8: A new video of my favorite band has been uploaded onto youtube.
A9: 8 | B9: My cell phone is out of service now because I’m in the basement.
A10: 9 | B10: This site is too heavy to browse.
A11: 10 | B11: Her new video has been uploaded on facebook.
A12: 11 | B12: I’ve updated my photos after my trip.
A13: 12 | B13: Youtube is too heavy to browse.
A14: 13 | B14: I use my phone to take photos.
A15: 14 | B15: My cell phone is out of service now because I am in the forest. | L15: 3
A16: 15 | B16: I use my phone to make a phone call.
A17: 16 | B17: I’ve updated a status on facebook.
A18: 17 | B18: I’ve updated my new profile picture on facebook.
A19: 18 | B19: My photo has been uploaded on facebook.
A20: 19 | B20: My Tam’s photos have been uploaded on her fanpage.
A21: 20 | B21: Technology has made my life easier.
A22: 21 | B22: I can work via facebook.
A23: 22 | B23: Technology has made my life more convenient.
A24: 23 | B24: My photo has been uploaded on facebook.
A25: 24 | B25: I can study via facebook.
A26: 25 | B26: I can connect with my friends via facebook.
A27: 26 | B27: Her new video has been uploaded on facebook.
... A32: 31 | B32: I can go shopping online via facebook.

Sheet 4
B1: The IT life
B2: 1. I set my cell phone to silent mode / airplane mode / night mode / meeting mode.
B3: 2. I recharge my cell phone twice a day / Can I recharge my cell phone here?
B4: 3. I connect the printer to the computer / my smartphone to the bluetooth speaker / my smartphone to the computer / my smartphone to wifi.
B5: 4. I take a photo / record a video / text a message / record with my cell phone camera and send it.
B6: 5. I respond to a message / email / comment.
B7: 6. I put a link in my post / my image / my email / my description.
B8: 7. I use my phone to make a phone call / to take photos / to access the internet / to send messages.
B9: 8. My cell phone is out of service now because I’m in the basement / I turn on the airplane mode / I am in the forest.
B10: 9. This site / Youtube / This music site is too heavy to browse.
B11: 10. I have updated a status on facebook / this page during my business trip / my new profile picture on facebook / my photos after my trip.
B12: 11. A new video of my favorite band / Her new video / My Tam’s photos / My photo has been uploaded onto youtube / on facebook / on her fanpage.
... B22: 21. I surf the internet in the middle of the night / early in the morning / in the office / during working hours quite often.

Sheet 3
A1: Shoppong
A2: 1. I got my socks / my clothes / decorative lights / wine wholesale.
A3: 2. Surplus goods / This books / These pizzas / This item are sold at half price.
A4: 3. I only buys brand-name products / shoes / glasses / handbag.
A5: 4. The night market / Farmer’s market / Flea market / Supermarket / The street is always crowded.
A6: 5. This is the only place that sells arts and crafts / handmade / free-range eggs and organic food / second-hand.
A7: 6. This book /These jeans / This item / This product is(are) too expensive / too cheap / reasonable.
A8: 7. How much does this computer / kettle / coats / bottle of perfume / pair of shoes /cup of coffee cost?
A9: 8. 60,000 dong for a cup of coffee / 600 dollars for this course / 2 million VND for this pair of shoes / 200,000 dong for this dish, what a rip-off!
A10: 9. This price is not within my budget / is negotiable / is fixed / seems fair / of this item is reasonable.
A11: 10. These items / The textbooks and dictionaries / All tickets / These gloves / This diamond ring are (is) on sale.
A12: 11. All products / This jacket / This couch / This skirt / This English course are (is) 10% off.
... A36: 34. I prefer my clothes to be a little loose / my clothes to be baggy / my clothes to be fashionable.
